Workbook
Name _2006_to_current_year: 'basic assumptions'!$D$57
Name _bookmark53: 'noise cost airports (not used)'!$A$3
Name _ftn1: 'Flight OPS costs (not used)'!$I$18
Name _ftnref1: 'Flight OPS costs (not used)'!$B$6
Name DE_factor06: 'basic assumptions'!$U$57
Name DE_factor07: 'basic assumptions'!$U$58
Name DE_factor08: 'basic assumptions'!$U$59
Name DE_factor09: 'basic assumptions'!$U$60
Name DE_factor10: 'basic assumptions'!$U$61
Name DE_factor11: 'basic assumptions'!$U$62
Name DE_factor12: 'basic assumptions'!$U$63
Name DE_factor13: 'basic assumptions'!$U$64
Name DE_factor14: 'basic assumptions'!$U$65
Name DE_factor15: 'basic assumptions'!$U$66
Name DE_factor16: 'basic assumptions'!$U$67
Name dollar: 'basic assumptions'!$H$7
Name dollar: #REF!
Name ExR_GBP_12: 'basic assumptions'!$I$5
Name ExR_GBP_13: 'basic assumptions'!$I$6
Name ExR_GBP_14: 'basic assumptions'!$I$7
Name ExR_GBP_17: 'basic assumptions'!$I$10
Name ExR_GBP_18: 'basic assumptions'!$I$11
Name ExR_GBP_19: 'basic assumptions'!$I$12
Name factor: 'basic assumptions'!$D$57
Name factor: #REF!
Name factor00: 'basic assumptions'!$D$51
Name factor01: 'basic assumptions'!$D$52
Name factor02: 'basic assumptions'!$D$53
Name factor03: 'basic assumptions'!$D$54
Name factor04: 'basic assumptions'!$D$55
Name factor05: 'basic assumptions'!$D$56
Name factor06: 'basic assumptions'!$D$57
Name factor07: 'basic assumptions'!$D$58
Name factor08: 'basic assumptions'!$D$59
Name factor09: 'basic assumptions'!$D$60
Name factor10: 'basic assumptions'!$D$61
Name factor11: 'basic assumptions'!$D$62
Name factor12: 'basic assumptions'!$D$63
Name factor13: 'basic assumptions'!$D$64
Name factor14: 'basic assumptions'!$D$65
Name factor15: 'basic assumptions'!$D$66
Name factor16: 'basic assumptions'!$D$67
Name factor17: 'basic assumptions'!$D$68
Name factor18: 'basic assumptions'!$D$69
Name factor19: 'basic assumptions'!$D$70
Name factor2006: 'basic assumptions'!$D$57
Name factor96: 'basic assumptions'!$D$47
Name factor97: 'basic assumptions'!$D$48
Name factor98: 'basic assumptions'!$D$49
Name factor99: 'basic assumptions'!$D$50
Name FR_factor06: 'basic assumptions'!$Q$57
Name FR_factor10: 'basic assumptions'!$Q$61
Name FR_factor11: 'basic assumptions'!$Q$62
Name FR_factor12: 'basic assumptions'!$Q$63
Name FR_factor15: 'basic assumptions'!$Q$66
Name FR_factor16: 'basic assumptions'!$Q$67
Name FR_factor17: 'basic assumptions'!$Q$68
Name FR_factor18: 'basic assumptions'!$Q$69
Name FR_factor19: 'basic assumptions'!$Q$70
Name index: 'basic assumptions'!$D$45

Sheet basic assumptions
C2: EUROPE | D2: http://ec.europa.eu/eurostat | L2: US | P2: France
D3: table prc_hicp_aind | G3: Exchange rates | L3: http://www.usinflationcalculator.com/inflation/current-inflation-rates/ | P3: EUROSTAT | T3: Germany | U3: EUROSTAT | X3: Italy | Y3: EUROSTAT | AB3: Spain | AC3: EUROSTAT | AF3: UK | AG3: EUROSTAT | AJ3: Netherlands | AK3: EUROSTAT
G4: year | H4: USD/Euro | I4: GBP/Euro
C5: Annual average inflation values | G5: 2012 | H5: 1.2848 | I5: 0.81087 | J5: ExR_GBP_12 | L5: Annual average inflation values | P5: Annual average inflation values | T5: Annual average inflation values | X5: Annual average inflation values | AB5: Annual average inflation values | AF5: Annual average inflation values | AJ5: Annual average inflation values
C6: Year | D6: Index | E6: Rate | G6: 2013 | H6: 1.3281 | I6: 0.84926 | J6: ExR_GBP_13 | L6: Year | M6: Index | N6: Rate | P6: Year | Q6: Index | R6: Rate | T6: Year | U6: Index | V6: Rate | X6: Year | Y6: Index | Z6: Rate | AB6: Year | AC6: Index | AD6: Rate | AF6: Year | AG6: Index | AH6: Rate | AJ6: Year | AK6: Index | AL6: Rate
C7: 1996 | D7: 70.34 | G7: 2014 | H7: 1.3285 | I7: 0.80612 | J7: ExR_GBP_14 | L7: 1996 | M7: 156.9 | N7: 3 | P7: 1996 | Q7: 74.93 | R7: 2.1 | T7: 1996 | U7: 76.2 | X7: 1996 | Y7: 68.5 | Z7: 4 | AB7: 1996 | AC7: 64.93 | AD7: 3.6 | AF7: 1996 | AG7: 68.8 | AH7: 2.5 | AJ7: 1996 | AK7: 68.83 | AL7: :
C8: 1997 | D8: 71.56 | E8: 0.017344328 | G8: 2015 | H8: 1.1095 | I8: 0.72584 | J8: ExR_GBP_15 | L8: 1997 | M8: 160.5 | N8: 2.3 | P8: 1997 | Q8: 75.88 | R8: =(Q8-Q7)/Q7 -> 0.0126785 | T8: 1997 | U8: 77.3 | V8: =(U8-U7)/U7 -> 0.014435696 | X8: 1997 | Y8: 69.8 | Z8: =(Y8-Y7)/Y7 -> 0.018978102 | AB8: 1997 | AC8: 66.15 | AD8: =(AC8-AC7)/AC7 -> 0.018789466 | AF8: 1997 | AG8: 70.1 | AH8: =(AG8-AG7)/AG7 -> 0.018895349 | AJ8: 1997 | AK8: 70.11 | AL8: =(AK8-AK7)/AK7 -> 0.018596542
C9: 1998 | D9: 72.48 | E9: 0.012856344 | G9: 2016 | H9: 1.1069 | I9: 0.81948 | J9: ExR_GBP_16 | L9: 1998 | M9: 163 | N9: 1.6 | P9: 1998 | Q9: 76.4 | R9: =(Q9-Q8)/Q8 -> 0.0068529257 | T9: 1998 | U9: 77.8 | V9: =(U9-U8)/U8 -> 0.0064683053 | X9: 1998 | Y9: 71.2 | Z9: =(Y9-Y8)/Y8 -> 0.020057307 | AB9: 1998 | AC9: 67.31 | AD9: =(AC9-AC8)/AC8 -> 0.017535903 | AF9: 1998 | AG9: 71.2 | AH9: =(AG9-AG8)/AG8 -> 0.015691869 | AJ9: 1998 | AK9: 71.36 | AL9: =(AK9-AK8)/AK8 -> 0.017829126
C10: 1999 | D10: 73.34 | E10: 0.011865342 | G10: 2017 | H10: 1.1297 | I10: 0.87667 | J10: ExR_GBP_17 | L10: 1999 | M10: 166.6 | N10: 2.2 | P10: 1999 | Q10: 76.83 | R10: =(Q10-Q9)/Q9 -> 0.0056282723 | T10: 1999 | U10: 78.3 | V10: =(U10-U9)/U9 -> 0.0064267352 | X10: 1999 | Y10: 72.3 | Z10: =(Y10-Y9)/Y9 -> 0.015449438 | AB10: 1999 | AC10: 68.82 | AD10: =(AC10-AC9)/AC9 -> 0.022433517 | AF10: 1999 | AG10: 72.1 | AH10: =(AG10-AG9)/AG9 -> 0.012640449 | AJ10: 1999 | AK10: 72.81 | AL10: =(AK10-AK9)/AK9 -> 0.020319507
C11: 2000 | D11: 74.73 | E11: 0.018952822 | G11: 2018 | H11: 1.181 | I11: 0.88471 | J11: ExR_GBP_18 | L11: 2000 | M11: 172.2 | N11: 3.4 | P11: 2000 | Q11: 78.23 | R11: =(Q11-Q10)/Q10 -> 0.018222049 | T11: 2000 | U11: 79.4 | V11: =(U11-U10)/U10 -> 0.014048531 | X11: 2000 | Y11: 74.2 | Z11: =(Y11-Y10)/Y10 -> 0.026279391 | AB11: 2000 | AC11: 71.22 | AD11: =(AC11-AC10)/AC10 -> 0.034873583 | AF11: 2000 | AG11: 72.7 | AH11: =(AG11-AG10)/AG10 -> 0.0083217753 | AJ11: 2000 | AK11: 74.51 | AL11: =(AK11-AK10)/AK10 -> 0.023348441
C12: 2001 | D12: 76.37 | E12: 0.021945671 | G12: 2019 | H12: 1.1195 | I12: 0.87777 | J12: ExR_GBP_19 | L12: 2001 | M12: 177.1 | N12: 2.8 | P12: 2001 | Q12: 79.62 | R12: =(Q12-Q11)/Q11 -> 0.01776812 | T12: 2001 | U12: 80.9 | V12: =(U12-U11)/U11 -> 0.018891688 | X12: 2001 | Y12: 75.9 | Z12: =(Y12-Y11)/Y11 -> 0.022911051 | AB12: 2001 | AC12: 73.23 | AD12: =(AC12-AC11)/AC11 -> 0.028222409 | AF12: 2001 | AG12: 73.6 | AH12: =(AG12-AG11)/AG11 -> 0.012379642 | AJ12: 2001 | AK12: 78.32 | AL12: =(AK12-AK11)/AK11 -> 0.051134076
C13: 2002 | D13: 77.96 | E13: 0.020819694 | G13: 2020 | L13: 2002 | M13: 179.9 | N13: 1.6 | P13: 2002 | Q13: 81.16 | R13: =(Q13-Q12)/Q12 -> 0.019341874 | T13: 2002 | U13: 82 | V13: =(U13-U12)/U12 -> 0.013597033 | X13: 2002 | Y13: 77.9 | Z13: =(Y13-Y12)/Y12 -> 0.026350461 | AB13: 2002 | AC13: 75.86 | AD13: =(AC13-AC12)/AC12 -> 0.035914243 | AF13: 2002 | AG13: 74.5 | AH13: =(AG13-AG12)/AG12 -> 0.012228261 | AJ13: 2002 | AK13: 81.35 | AL13: =(AK13-AK12)/AK12 -> 0.038687436
C14: 2003 | D14: 79.49 | E14: 0.019625449 | G14: 2021 | L14: 2003 | M14: 184 | N14: 2.3 | P14: 2003 | Q14: 82.93 | R14: =(Q14-Q13)/Q13 -> 0.021808773 | T14: 2003 | U14: 82.8 | V14: =(U14-U13)/U13 -> 0.0097560976 | X14: 2003 | Y14: 80.1 | Z14: =(Y14-Y13)/Y13 -> 0.028241335 | AB14: 2003 | AC14: 78.21 | AD14: =(AC14-AC13)/AC13 -> 0.030978118 | AF14: 2003 | AG14: 75.5 | AH14: =(AG14-AG13)/AG13 -> 0.013422819 | AJ14: 2003 | AK14: 83.16 | AL14: =(AK14-AK13)/AK13 -> 0.022249539
C15: 2004 | D15: 81.09 | E15: 0.020128318 | G15: 2022 | L15: 2004 | M15: 188.9 | N15: 2.7 | P15: 2004 | Q15: 84.86 | R15: =(Q15-Q14)/Q14 -> 0.02327264 | T15: 2004 | U15: 84.3 | V15: =(U15-U14)/U14 -> 0.018115942 | X15: 2004 | Y15: 81.9 | Z15: =(Y15-Y14)/Y14 -> 0.02247191 | AB15: 2004 | AC15: 80.6 | AD15: =(AC15-AC14)/AC14 -> 0.030558752 | AF15: 2004 | AG15: 76.5 | AH15: =(AG15-AG14)/AG14 -> 0.013245033 | AJ15: 2004 | AK15: 84.32 | AL15: =(AK15-AK14)/AK14 -> 0.013949014
C16: 2005 | D16: 82.85 | E16: 0.021704279 | G16: 2023 | L16: 2005 | M16: 195.3 | N16: 3.4 | P16: 2005 | Q16: 86.47 | R16: =(Q16-Q15)/Q15 -> 0.018972425 | T16: 2005 | U16: 85.5 | V16: =(U16-U15)/U15 -> 0.014234875 | X16: 2005 | Y16: 83.7 | Z16: =(Y16-Y15)/Y15 -> 0.021978022 | AB16: 2005 | AC16: 83.33 | AD16: =(AC16-AC15)/AC15 -> 0.033870968 | AF16: 2005 | AG16: 78.1 | AH16: =(AG16-AG15)/AG15 -> 0.020915033 | AJ16: 2005 | AK16: 85.57 | AL16: =(AK16-AK15)/AK15 -> 0.014824478
C17: 2006 | D17: 84.67 | E17: 0.021967411 | L17: 2006 | M17: 201.6 | N17: 3.2 | P17: 2006 | Q17: 88.1 | R17: =(Q17-Q16)/Q16 -> 0.018850468 | T17: 2006 | U17: 87 | V17: =(U17-U16)/U16 -> 0.01754386 | X17: 2006 | Y17: 85.6 | Z17: =(Y17-Y16)/Y16 -> 0.022700119 | AB17: 2006 | AC17: 86.29 | AD17: =(AC17-AC16)/AC16 -> 0.035521421 | AF17: 2006 | AG17: 79.9 | AH17: =(AG17-AG16)/AG16 -> 0.023047375 | AJ17: 2006 | AK17: 86.99 | AL17: =(AK17-AK16)/AK16 -> 0.016594601
C18: 2007 | D18: 86.65 | E18: 0.023384906 | L18: 2007 | M18: 207.3 | N18: 2.8 | P18: 2007 | Q18: 89.52 | R18: =(Q18-Q17)/Q17 -> 0.016118048 | T18: 2007 | U18: 89 | V18: =(U18-U17)/U17 -> 0.022988506 | X18: 2007 | Y18: 87.3 | Z18: =(Y18-Y17)/Y17 -> 0.019859813 | AB18: 2007 | AC18: 88.75 | AD18: =(AC18-AC17)/AC17 -> 0.028508518 | AF18: 2007 | AG18: 81.8 | AH18: =(AG18-AG17)/AG17 -> 0.023779725 | AJ18: 2007 | AK18: 88.36 | AL18: =(AK18-AK17)/AK17 -> 0.015748937
C19: 2008 | D19: 89.72 | E19: 0.03542989 | L19: 2008 | M19: 215.303 | N19: 3.8 | P19: 2008 | Q19: 92.34 | R19: =(Q19-Q18)/Q18 -> 0.03150134 | T19: 2008 | U19: 91.4 | V19: =(U19-U18)/U18 -> 0.026966292 | X19: 2008 | Y19: 90.4 | Z19: =(Y19-Y18)/Y18 -> 0.035509737 | AB19: 2008 | AC19: 92.41 | AD19: =(AC19-AC18)/AC18 -> 0.041239437 | AF19: 2008 | AG19: 84.7 | AH19: =(AG19-AG18)/AG18 -> 0.035452323 | AJ19: 2008 | AK19: 90.32 | AL19: =(AK19-AK18)/AK18 -> 0.022181983
C20: 2009 | D20: 90.6 | E20: 0.0098082925 | L20: 2009 | M20: 214.537 | N20: -0.4 | P20: 2009 | Q20: 92.44 | R20: =(Q20-Q19)/Q19 -> 0.0010829543 | T20: 2009 | U20: 91.6 | V20: =(U20-U19)/U19 -> 0.0021881838 | X20: 2009 | Y20: 91.1 | Z20: =(Y20-Y19)/Y19 -> 0.0077433628 | AB20: 2009 | AC20: 92.19 | AD20: =(AC20-AC19)/AC19 -> -0.0023806947 | AF20: 2009 | AG20: 86.6 | AH20: =(AG20-AG19)/AG19 -> 0.022432113 | AJ20: 2009 | AK20: 91.2 | AL20: =(AK20-AK19)/AK19 -> 0.0097431355
C21: 2010 | D21: 92.49 | E21: 0.020860927 | L21: 2010 | M21: 218.056 | N21: 1.6 | P21: 2010 | Q21: 94.05 | R21: =(Q21-Q20)/Q20 -> 0.017416703 | T21: 2010 | U21: 92.7 | V21: =(U21-U20)/U20 -> 0.012008734 | X21: 2010 | Y21: 92.6 | Z21: =(Y21-Y20)/Y20 -> 0.016465423 | AB21: 2010 | AC21: 94.08 | AD21: =(AC21-AC20)/AC20 -> 0.020501139 | AF21: 2010 | AG21: 89.4 | AH21: =(AG21-AG20)/AG20 -> 0.032332564 | AJ21: 2010 | AK21: 92.05 | AL21: =(AK21-AK20)/AK20 -> 0.0093201754
C22: 2011 | D22: 95.36 | E22: 0.031030382 | L22: 2011 | M22: 224.939 | N22: 3.2 | P22: 2011 | Q22: 96.2 | R22: =(Q22-Q21)/Q21 -> 0.022860181 | T22: 2011 | U22: 95 | V22: =(U22-U21)/U21 -> 0.024811219 | X22: 2011 | Y22: 95.3 | Z22: =(Y22-Y21)/Y21 -> 0.029157667 | AB22: 2011 | AC22: 96.94 | AD22: =(AC22-AC21)/AC21 -> 0.03039966 | AF22: 2011 | AG22: 93.4 | AH22: =(AG22-AG21)/AG21 -> 0.044742729 | AJ22: 2011 | AK22: 94.32 | AL22: =(AK22-AK21)/AK21 -> 0.024660511
C23: 2012 | D23: 97.88 | E23: 0.026426174 | L23: 2012 | M23: 229.594 | N23: 2.1 | P23: 2012 | Q23: 98.33 | R23: =(Q23-Q22)/Q22 -> 0.022141372 | T23: 2012 | U23: 97 | V23: =(U23-U22)/U22 -> 0.021052632 | X23: 2012 | Y23: 98.4 | Z23: =(Y23-Y22)/Y22 -> 0.032528856 | AB23: 2012 | AC23: 99.31 | AD23: =(AC23-AC22)/AC22 -> 0.024448112 | AF23: 2012 | AG23: 96.1 | AH23: =(AG23-AG22)/AG22 -> 0.028907923 | AJ23: 2012 | AK23: 96.99 | AL23: =(AK23-AK22)/AK22 -> 0.028307888
C24: 2013 | D24: 99.35 | E24: 0.01501839 | L24: 2013 | M24: 232.957 | N24: 1.5 | P24: 2013 | Q24: 99.31 | R24: =(Q24-Q23)/Q23 -> 0.0099664395 | T24: 2013 | U24: 98.6 | V24: =(U24-U23)/U23 -> 0.016494845 | X24: 2013 | Y24: 99.7 | Z24: =(Y24-Y23)/Y23 -> 0.013211382 | AB24: 2013 | AC24: 100.83 | AD24: =(AC24-AC23)/AC23 -> 0.015305609 | AF24: 2013 | AG24: 98.5 | AH24: =(AG24-AG23)/AG23 -> 0.024973985 | AJ24: 2013 | AK24: 99.47 | AL24: =(AK24-AK23)/AK23 -> 0.025569646
C25: 2014 | D25: 99.9 | E25: 0.0055359839 | L25: 2014 | M25: 236.736 | N25: 1.6 | P25: 2014 | Q25: 99.91 | R25: =(Q25-Q24)/Q24 -> 0.0060416876 | T25: 2014 | U25: 99.3 | V25: =(U25-U24)/U24 -> 0.0070993915 | X25: 2014 | Y25: 99.9 | Z25: =(Y25-Y24)/Y24 -> 0.0020060181 | AB25: 2014 | AC25: 100.63 | AD25: =(AC25-AC24)/AC24 -> -0.0019835366 | AF25: 2014 | AG25: 100 | AH25: =(AG25-AG24)/AG24 -> 0.015228426 | AJ25: 2014 | AK25: 99.79 | AL25: =(AK25-AK24)/AK24 -> 0.0032170504
C26: 2015 | D26: 100 | E26: 0.001001001 | L26: 2015 | M26: 237.017 | N26: 0.1 | P26: 2015 | Q26: 100 | R26: =(Q26-Q25)/Q25 -> 0.00090081073 | T26: 2015 | U26: 100 | V26: =(U26-U25)/U25 -> 0.0070493454 | X26: 2015 | Y26: 100 | Z26: =(Y26-Y25)/Y25 -> 0.001001001 | AB26: 2015 | AC26: 100 | AD26: =(AC26-AC25)/AC25 -> -0.0062605585 | AF26: 2015 | AG26: 100 | AH26: =(AG26-AG25)/AG25 -> 0 | AJ26: 2015 | AK26: 100 | AL26: =(AK26-AK25)/AK25 -> 0.0021044193
C27: 2016 | D27: 100.25 | E27: 0.0025 | L27: 2016 | M27: 240.007 | N27: 1.3 | P27: 2016 | Q27: 100.31 | R27: =(Q27-Q26)/Q26 -> 0.0031 | T27: 2016 | U27: 100.4 | V27: =(U27-U26)/U26 -> 0.004 | X27: 2016 | Y27: 99.9 | Z27: =(Y27-Y26)/Y26 -> -0.001 | AB27: 2016 | AC27: 99.66 | AD27: =(AC27-AC26)/AC26 -> -0.0034 | AF27: 2016 | AG27: 100.7 | AH27: =(AG27-AG26)/AG26 -> 0.007 | AJ27: 2016 | AK27: 100.11 | AL27: =(AK27-AK26)/AK26 -> 0.0011
C28: 2017 | D28: 101.96 | E28: 0.017057357 | L28: 2017 | M28: 245.12 | N28: 2.1 | P28: 2017 | Q28: 101.47 | R28: =(Q28-Q27)/Q27 -> 0.011564151 | T28: 2017 | U28: 102.1 | V28: =(U28-U27)/U27 -> 0.016932271 | X28: 2017 | Y28: 101.3 | Z28: =(Y28-Y27)/Y27 -> 0.014014014 | AB28: 2017 | AC28: 101.69 | AD28: =(AC28-AC27)/AC27 -> 0.020369255 | AF28: 2017 | AG28: 103.4 | AH28: =(AG28-AG27)/AG27 -> 0.026812314 | AJ28: 2017 | AK28: 101.4 | AL28: =(AK28-AK27)/AK27 -> 0.012885826
... C30: 2019 | D30: 105.42 | E30: 0.014727115 | L30: 2019 | M30: 255.657 | N30: 1.8 | P30: 2019 | Q30: 104.95 | R30: =(Q30-Q29)/Q29 -> 0.013030888 | T30: 2019 | U30: 105.5 | V30: =(U30-U29)/U29 -> 0.014423077 | X30: 2019 | Y30: 103.2 | Z30: =(Y30-Y29)/Y29 -> 0.0068292683 | AB30: 2019 | AC30: 104.26 | AD30: =(AC30-AC29)/AC29 -> 0.007732457 | AF30: 2019 | AG30: 107.8 | AH30: =(AG30-AG29)/AG29 -> 0.017941454 | AJ30: 2019 | AK30: 105.78 | AL30: =(AK30-AK29)/AK29 -> 0.026790914
C31: 2020 | D31: 105.8 | E31: 0.0036046291 | L31: 2020 | M31: 258.8 | N31: 1.2 | P31: 2020 | T31: 2020 | X31: 2020 | AB31: 2020 | AF31: 2020 | AJ31: 2020
C32: 2021 | D32: 108.8 | E32: 0.028355388 | L32: 2021 | M32: 271 | N32: 4.7 | P32: 2021 | T32: 2021 | X32: 2021 | AB32: 2021 | AF32: 2021 | AJ32: 2021
C33: 2022 | D33: 118.8 | E33: 0.091911765 | L33: 2022 | M33: 292.655 | N33: 8 | P33: 2022 | T33: 2022 | X33: 2022 | AB33: 2022 | AF33: 2022 | AJ33: 2022
C34: 2023 | D34: 126.38 | E34: 0.063804714 | L34: 2023 | M34: 304.746 | N34: 4.1
C35: 2024 | D35: 129.67 | E35: 0.0260326 | L35: 2024 | M35: 313.689 | N35: 2.9
C36: 2025 | D36: 132.86 | E36: 0.02460091 | L36: 2025 | M36: 321.943 | N36: 2.6
C45: Current year | D45: =D30 -> 105.42 | E45: index | L45: Current year | M45: =M30 -> 255.657 | N45: indexUS | P45: Current year | Q45: =Q30 -> 104.95 | R45: indexFR | T45: Current year | U45: =U30 -> 105.5 | V45: indexDE | X45: Current year | Y45: =Y30 -> 103.2 | Z45: indexIT | AB45: Current year | AC45: =AC30 -> 104.26 | AD45: indexSP | AF45: Current year | AG45: =AG30 -> 107.8 | AH45: indexUK | AJ45: Current year | AK45: =AK30 -> 105.78 | AL45: indexNL
C47: 1996 to current year | D47: =index/D7 -> 1.4987205 | E47: factor96 | L47: 1996 to current year | M47: =indexUS/M7 -> 1.6294264 | N47: US_factor96 | P47: 1996 to current year | Q47: =indexFR/Q7 -> 1.4006406 | R47: FR_factor96 | T47: 1996 to current year | U47: =indexDE/U7 -> 1.3845144 | V47: DE_factor96 | X47: 1996 to current year | Y47: =indexIT/Y7 -> 1.5065693 | Z47: IT_factor96 | AB47: 1996 to current year | AC47: =indexSP/AC7 -> 1.6057292 | AD47: SP_factor96 | AF47: 1996 to current year | AG47: =indexUK/AG7 -> 1.5668605 | AH47: UK_factor96 | AJ47: 1996 to current year | AK47: =indexNL/AK7 -> 1.5368299 | AL47: NL_factor96
C48: 1997 to current year | D48: =index/D8 -> 1.4731694 | E48: factor97 | L48: 1997 to current year | M48: =indexUS/M8 -> 1.5928785 | N48: US_factor97 | P48: 1997 to current year | Q48: =indexFR/Q8 -> 1.3831049 | R48: FR_factor97 | T48: 1997 to current year | U48: =indexDE/U8 -> 1.3648124 | V48: DE_factor97 | X48: 1997 to current year | Y48: =indexIT/Y8 -> 1.47851 | Z48: IT_factor97 | AB48: 1997 to current year | AC48: =indexSP/AC8 -> 1.5761149 | AD48: SP_factor97 | AF48: 1997 to current year | AG48: =indexUK/AG8 -> 1.5378031 | AH48: UK_factor97 | AJ48: 1997 to current year | AK48: =indexNL/AK8 -> 1.5087719 | AL48: NL_factor97
C49: 1998 to current year | D49: =index/D9 -> 1.4544702 | E49: factor98 | L49: 1998 to current year | M49: =indexUS/M9 -> 1.5684479 | N49: US_factor98 | P49: 1998 to current year | Q49: =indexFR/Q9 -> 1.3736911 | R49: FR_factor98 | T49: 1998 to current year | U49: =indexDE/U9 -> 1.3560411 | V49: DE_factor98 | X49: 1998 to current year | Y49: =indexIT/Y9 -> 1.4494382 | Z49: IT_factor98 | AB49: 1998 to current year | AC49: =indexSP/AC9 -> 1.5489526 | AD49: SP_factor98 | AF49: 1998 to current year | AG49: =indexUK/AG9 -> 1.5140449 | AH49: UK_factor98 | AJ49: 1998 to current year | AK49: =indexNL/AK9 -> 1.482343 | AL49: NL_factor98
C50: 1999 to current year | D50: =index/D10 -> 1.4374148 | E50: factor99 | L50: 1999 to current year | M50: =indexUS/M10 -> 1.5345558 | N50: US_factor99 | P50: 1999 to current year | Q50: =indexFR/Q10 -> 1.3660029 | R50: FR_factor99 | T50: 1999 to current year | U50: =indexDE/U10 -> 1.3473819 | V50: DE_factor99 | X50: 1999 to current year | Y50: =indexIT/Y10 -> 1.4273859 | Z50: IT_factor99 | AB50: 1999 to current year | AC50: =indexSP/AC10 -> 1.5149666 | AD50: SP_factor99 | AF50: 1999 to current year | AG50: =indexUK/AG10 -> 1.4951456 | AH50: UK_factor99 | AJ50: 1999 to current year | AK50: =indexNL/AK10 -> 1.4528224 | AL50: NL_factor99
C51: 2000 to current year | D51: =index/D11 -> 1.4106784 | E51: factor00 | L51: 2000 to current year | M51: =indexUS/M11 -> 1.4846516 | N51: US_factor00 | P51: 2000 to current year | Q51: =indexFR/Q11 -> 1.3415569 | R51: FR_factor00 | T51: 2000 to current year | U51: =indexDE/U11 -> 1.3287154 | V51: DE_factor00 | X51: 2000 to current year | Y51: =indexIT/Y11 -> 1.3908356 | Z51: IT_factor00 | AB51: 2000 to current year | AC51: =indexSP/AC11 -> 1.4639146 | AD51: SP_factor00 | AF51: 2000 to current year | AG51: =indexUK/AG11 -> 1.4828061 | AH51: UK_factor00 | AJ51: 2000 to current year | AK51: =indexNL/AK11 -> 1.4196752 | AL51: NL_factor00
C52: 2001 to current year | D52: =index/D12 -> 1.380385 | E52: factor01 | L52: 2001 to current year | M52: =indexUS/M12 -> 1.4435743 | N52: US_factor01 | P52: 2001 to current year | Q52: =indexFR/Q12 -> 1.3181361 | R52: FR_factor01 | T52: 2001 to current year | U52: =indexDE/U12 -> 1.3040791 | V52: DE_factor01 | X52: 2001 to current year | Y52: =indexIT/Y12 -> 1.3596838 | Z52: IT_factor01 | AB52: 2001 to current year | AC52: =indexSP/AC12 -> 1.4237334 | AD52: SP_factor01 | AF52: 2001 to current year | AG52: =indexUK/AG12 -> 1.4646739 | AH52: UK_factor01 | AJ52: 2001 to current year | AK52: =indexNL/AK12 -> 1.3506129 | AL52: NL_factor01
C53: 2002 to current year | D53: =index/D13 -> 1.3522319 | E53: factor02 | L53: 2002 to current year | M53: =indexUS/M13 -> 1.4211062 | N53: US_factor02 | P53: 2002 to current year | Q53: =indexFR/Q13 -> 1.2931247 | R53: FR_factor02 | T53: 2002 to current year | U53: =indexDE/U13 -> 1.2865854 | V53: DE_factor02 | X53: 2002 to current year | Y53: =indexIT/Y13 -> 1.3247754 | Z53: IT_factor02 | AB53: 2002 to current year | AC53: =indexSP/AC13 -> 1.3743738 | AD53: SP_factor02 | AF53: 2002 to current year | AG53: =indexUK/AG13 -> 1.4469799 | AH53: UK_factor02 | AJ53: 2002 to current year | AK53: =indexNL/AK13 -> 1.3003073 | AL53: NL_factor02
C54: 2003 to current year | D54: =index/D14 -> 1.3262046 | E54: factor03 | L54: 2003 to current year | M54: =indexUS/M14 -> 1.3894402 | N54: US_factor03 | P54: 2003 to current year | Q54: =indexFR/Q14 -> 1.2655251 | R54: FR_factor03 | T54: 2003 to current year | U54: =indexDE/U14 -> 1.2741546 | V54: DE_factor03 | X54: 2003 to current year | Y54: =indexIT/Y14 -> 1.2883895 | Z54: IT_factor03 | AB54: 2003 to current year | AC54: =indexSP/AC14 -> 1.3330776 | AD54: SP_factor03 | AF54: 2003 to current year | AG54: =indexUK/AG14 -> 1.4278146 | AH54: UK_factor03 | AJ54: 2003 to current year | AK54: =indexNL/AK14 -> 1.2720058 | AL54: NL_factor03
C55: 2004 to current year | D55: =index/D15 -> 1.300037 | E55: factor04 | L55: 2004 to current year | M55: =indexUS/M15 -> 1.3533986 | N55: US_factor04 | P55: 2004 to current year | Q55: =indexFR/Q15 -> 1.2367429 | R55: FR_factor04 | T55: 2004 to current year | U55: =indexDE/U15 -> 1.2514828 | V55: DE_factor04 | X55: 2004 to current year | Y55: =indexIT/Y15 -> 1.2600733 | Z55: IT_factor04 | AB55: 2004 to current year | AC55: =indexSP/AC15 -> 1.2935484 | AD55: SP_factor04 | AF55: 2004 to current year | AG55: =indexUK/AG15 -> 1.4091503 | AH55: UK_factor04 | AJ55: 2004 to current year | AK55: =indexNL/AK15 -> 1.2545066 | AL55: NL_factor04
C56: 2005 to current year | D56: =index/D16 -> 1.27242 | E56: factor05 | L56: 2005 to current year | M56: =indexUS/M16 -> 1.3090476 | N56: US_factor05 | P56: 2005 to current year | Q56: =indexFR/Q16 -> 1.2137157 | R56: FR_factor05 | T56: 2005 to current year | U56: =indexDE/U16 -> 1.2339181 | V56: DE_factor05 | X56: 2005 to current year | Y56: =indexIT/Y16 -> 1.2329749 | Z56: IT_factor05 | AB56: 2005 to current year | AC56: =indexSP/AC16 -> 1.25117 | AD56: SP_factor05 | AF56: 2005 to current year | AG56: =indexUK/AG16 -> 1.3802817 | AH56: UK_factor05 | AJ56: 2005 to current year | AK56: =indexNL/AK16 -> 1.2361809 | AL56: NL_factor05
C57: 2006 to current year | D57: =index/D17 -> 1.2450691 | E57: factor06 | L57: 2006 to current year | M57: =indexUS/M17 -> 1.2681399 | N57: US_factor06 | P57: 2006 to current year | Q57: =indexFR/Q17 -> 1.1912599 | R57: FR_factor06 | T57: 2006 to current year | U57: =indexDE/U17 -> 1.2126437 | V57: DE_factor06 | X57: 2006 to current year | Y57: =indexIT/Y17 -> 1.2056075 | Z57: IT_factor06 | AB57: 2006 to current year | AC57: =indexSP/AC17 -> 1.2082512 | AD57: SP_factor06 | AF57: 2006 to current year | AG57: =indexUK/AG17 -> 1.3491865 | AH57: UK_factor06 | AJ57: 2006 to current year | AK57: =indexNL/AK17 -> 1.2160018 | AL57: NL_factor06
C58: 2007 to current year | D58: =index/D18 -> 1.2166186 | E58: factor07 | L58: 2007 to current year | M58: =indexUS/M18 -> 1.2332706 | N58: US_factor07 | P58: 2007 to current year | Q58: =indexFR/Q18 -> 1.1723637 | R58: FR_factor07 | T58: 2007 to current year | U58: =indexDE/U18 -> 1.1853933 | V58: DE_factor07 | X58: 2007 to current year | Y58: =indexIT/Y18 -> 1.1821306 | Z58: IT_factor07 | AB58: 2007 to current year | AC58: =indexSP/AC18 -> 1.1747606 | AD58: SP_factor07 | AF58: 2007 to current year | AG58: =indexUK/AG18 -> 1.3178484 | AH58: UK_factor07 | AJ58: 2007 to current year | AK58: =indexNL/AK18 -> 1.197148 | AL58: NL_factor07
... C70: 2019 to current year | D70: =index/D30 -> 1 | E70: factor19 | L70: 2019 to current year | M70: =indexUS/M30 -> 1 | N70: US_factor19 | P70: 2019 to current year | Q70: =indexFR/Q30 -> 1 | R70: FR_factor19 | T70: 2019 to current year | U70: =indexDE/U30 -> 1 | V70: DE_factor19 | X70: 2019 to current year | Y70: =indexIT/Y30 -> 1 | Z70: IT_factor19 | AB70: 2019 to current year | AC70: =indexSP/AC30 -> 1 | AD70: SP_factor19 | AF70: 2019 to current year | AG70: =indexUK/AG30 -> 1 | AH70: UK_factor19 | AJ70: 2019 to current year | AK70: =indexNL/AK30 -> 1 | AL70: NL_factor19

Sheet Cancellation cost
B2: 2014
B4: Cost of Cancellation | C4: Narrowbody | G4: Widebody | J4: System wide average cancellation cost
C5: Traditional Network | F5: Low Cost Carrier | G5: Traditional Network Carrier
C6: Carrier[1] | J6: 17600
B7: Seats | C7: 50 | D7: 120 | E7: 180 | F7: 189 | G7: 250 | H7: 400
B8: Proposed value (€) | C8: 6200 | D8: 15200 | E8: 23600 | F8: 18400 | G8: 78400 | H8: 114500 | J8: 17600
B9: of which passenger care & compensation (€) | C9: 3100 | D9: 7600 | E9: 12400 | F9: 17500 | G9: 40500 | H9: 64800
B12: [1] Traditional carrier estimates can be used for regional carriers.
B17: 2016
B19: Cost of Cancellation | C19: Narrowbody | G19: Widebody | J19: System wide average cancellation cost
C20: Traditional Network | F20: Low Cost Carrier | G20: Traditional Network Carrier
C21: Carrier[1] | J21: 17600
B22: Seats | C22: 50 | D22: 120 | E22: 180 | F22: 189 | G22: 250 | H22: 400
B23: Proposed value (€) | C23: =ROUNDUP(C8*'basic assumptions'!$D$27/100,0) -> 6216 | D23: =ROUNDUP(D8*'basic assumptions'!$D$27/100,0) -> 15238 | E23: =ROUNDUP(E8*'basic assumptions'!$D$27/100,0) -> 23659 | F23: =ROUNDUP(F8*'basic assumptions'!$D$27/100,0) -> 18446 | G23: =ROUNDUP(G8*'basic assumptions'!$D$27/100,0) -> 78596 | H23: =ROUNDUP(H8*'basic assumptions'!$D$27/100,0) -> 114787 | J23: =J8*'basic assumptions'!D27/100 -> 17644
B24: of which passenger care & compensation (€) | C24: =ROUND(C9*'basic assumptions'!$D$27/100,0) -> 3108 | D24: =ROUND(D9*'basic assumptions'!$D$27/100,0) -> 7619 | E24: =ROUND(E9*'basic assumptions'!$D$27/100,0) -> 12431 | F24: =ROUND(F9*'basic assumptions'!$D$27/100,0) -> 17544 | G24: =ROUND(G9*'basic assumptions'!$D$27/100,0) -> 40601 | H24: =ROUND(H9*'basic assumptions'!$D$27/100,0) -> 64962
B27: value 2016 rounded
B29: Cost of Cancellation | C29: Narrowbody | G29: Widebody | J29: System wide average cancellation cost
C30: Traditional Network | F30: Low Cost Carrier | G30: Traditional Network Carrier
C31: Carrier[1] | J31: 17600
B32: Seats | C32: 50 | D32: 120 | E32: 180 | F32: 189 | G32: 250 | H32: 400
B33: Proposed value (€) | C33: 6220 | D33: 15240 | E33: 23660 | F33: 18450 | G33: 78600 | H33: 114790 | J33: 17650
B34: of which passenger care & compensation (€) | C34: 3110 | D34: 7620 | E34: 12430 | F34: 17540 | G34: 40600 | H34: 64970
B38: value 2019
B40: Cost of Cancellation | C40: Narrowbody | G40: Widebody | J40: System wide average cancellation cost
C41: Traditional Network | F41: Low Cost Carrier | G41: Traditional Network Carrier
C42: Carrier[1] | J42: 17600
B43: Seats | C43: 50 | D43: 120 | E43: 180 | F43: 189 | G43: 250 | H43: 400
B44: Proposed value (€) | C44: =C8*factor14 -> 6542.5826 | D44: =D8*factor14 -> 16039.88 | E44: =E8*factor14 -> 24904.024 | F44: =F8*factor14 -> 19416.697 | G44: =G8*factor14 -> 82732.012 | H44: =H8*factor14 -> 120826.73 | J44: =J8*factor14 -> 18572.492
B45: of which passenger care & compensation (€) | C45: =C9*factor14 -> 3271.2913 | D45: =D9*factor14 -> 8019.9399 | E45: =E9*factor14 -> 13085.165 | F45: =F9*factor14 -> 18466.967 | G45: =G9*factor14 -> 42737.838 | H45: =H9*factor14 -> 68380.541
B48: value 2019 rounded
B50: Cost of Cancellation | C50: Narrowbody | G50: Widebody | J50: System wide average cancellation cost
C51: Traditional Network | F51: Low Cost Carrier | G51: Traditional Network Carrier
C52: Carrier[1] | J52: 17600
B53: Seats | C53: 50 | D53: 120 | E53: 180 | F53: 189 | G53: 250 | H53: 400
B54: Proposed value (€) | C54: =ROUND(C44,-1) -> 6540 | D54: =ROUND(D44,-1) -> 16040 | E54: =ROUND(E44,-1) -> 24900 | F54: =ROUND(F44,-1) -> 19420 | G54: =ROUND(G44,-1) -> 82730 | H54: =ROUND(H44,-1) -> 120830 | J54: =ROUND(J44,-1) -> 18570
B55: of which passenger care & compensation (€) | C55: =ROUNDUP(C45,-1) -> 3280 | D55: =ROUNDUP(D45,-1) -> 8020 | E55: =ROUNDUP(E45,-1) -> 13090 | F55: =ROUNDUP(F45,-1) -> 18470 | G55: =ROUNDUP(G45,-1) -> 42740 | H55: =ROUNDUP(H45,-1) -> 68390

Sheet Cancellation_Diversion
A1: Cancellation cost | B1: source
A2: Reommended Value | B2: SESAR evaluation team 2006 | C2: Typical values are:
A3: 50 seat narrow body aircraft | C3: 3200 | F3: =C3*factor06 -> 3984.2211
A4: 120 seat narrow body aircraft | C4: 15000 | F4: =C4*factor06 -> 18676.036
A5: 400 seat wide body aircraft | C5: 70000 | F5: =C5*factor06 -> 87154.836
A7: Other Value: | B7: EGNOS CBA | C7: € 6,680 per cancellation | D7: 5700 | E7: =D7*#REF!/#REF! -> #REF! | F7: =D7*factor99 -> 8193.2642
A9: Diversion cost | H9: rounded
A10: Recommended Value: | F10: 2019
A11: Regional flights | B11: 2006 price | C11: 700 | D11: 5000 | E11: =C11*factor06 -> 871.54836 | F11: =D11*factor06 -> 6225.3455 | H11: =ROUND(E11,-2) -> 900 | I11: =ROUND(F11,-2) -> 6200
A12: Continental flights | B12: 2006 price | C12: 1000 | D12: 7500 | E12: =C12*factor06 -> 1245.0691 | F12: =D12*factor06 -> 9338.0182 | H12: =ROUND(E12,-2) -> 1200 | I12: =ROUND(F12,-2) -> 9300
A13: Intercontinental flights | B13: 2006 price | C13: 5000 | D13: 55000 | E13: =C13*factor06 -> 6225.3455 | F13: =D13*factor06 -> 68478.8 | H13: =ROUND(E13,-2) -> 6200 | I13: =ROUND(F13,-2) -> 68500
A15: Business Aviation | B15: 2012 price | C15: 7243 | F15: =C15*factor12 -> 7800.9508 | H15: =ROUND(F15,-2) -> 7800
A20: 120 seat narrow body aircraft | C20: 5000 | F20: =C20*factor06 -> 6225.3455
A21: 400 seat wide body aircraft | C21: 17000 | F21: =C21*factor06 -> 21166.175
A23: Other Value: | C23: € 4,760 per diversion | F23: =F26*factor99 -> 8402.3891
B25: Time lost (min) | C25: Cost/min (€) | D25: No of passengers | E25: Cost/pax/hr (€) | F25: Total (€)
B26: 50 | C26: =24*factor99 -> 34.497955 | D26: 43 | E26: =80*factor99 -> 114.99318 | F26: =B26*(C26+D26*E26/60) -> 5845.4868

Sheet Cost of  Delay
S6: 2016 values | AF6: 2019 values
C7: 2016 values | F7: 2019 values | J7: Aircraft type | K7: Delay ranges (mins) | X7: Aircraft type | Y7: Delay ranges (mins)
C8: all delays (up to 300 minutes) | D8: 90% of delays (0 to 30 minutes) | F8: all delays (up to 300 minutes) | G8: 90% of delays (0 to 30 minutes) | K8: At-gate | N8: Taxi | Q8: En route | T8: Arrival Mgt | Y8: At-gate | AB8: Taxi | AE8: En route | AH8: Arrival Mgt
K9: 5' | L9: 15' | M9: 30' | N9: 5' | O9: 15' | P9: 30' | Q9: 5' | R9: 15' | S9: 30' | T9: 5' | U9: 15' | V9: 30' | Y9: 5' | Z9: 15' | AA9: 30' | AB9: 5' | AC9: 15' | AD9: 30' | AE9: 5' | AF9: 15' | AG9: 30' | AH9: 5' | AI9: 15' | AJ9: 30'
A10: Ground | B10: At-Gate | C10: 140 | D10: 38 | F10: =C10*factor16 -> 147.21995 | G10: =D10*factor16 -> 39.959701 | J10: A319 | K10: 70 | L10: 441 | M10: 1604 | N10: 130 | O10: 611 | P10: 1945 | Q10: 241 | R10: 952 | S10: 2626 | T10: 221 | U10: 892 | V10: 2516 | X10: =J10 -> A319 | Y10: =K10*factor16 -> 73.609975 | Z10: =L10*factor16 -> 463.74284 | AA10: =M10*factor16 -> 1686.72 | AB10: =N10*factor16 -> 136.70424 | AC10: =O10*factor16 -> 642.50993 | AD10: =P10*factor16 -> 2045.3057 | AE10: =Q10*factor16 -> 253.42863 | AF10: =R10*factor16 -> 1001.0957 | ... AJ10: =V10*factor16 -> 2645.7528
B11: Taxi in/out | C11: 154 | D11: 52 | F11: =C11*factor16 -> 161.94195 | G11: =D11*factor16 -> 54.681696 | J11: A320 | K11: 80 | L11: 501 | M11: 1824 | N11: 150 | O11: 712 | P11: 2255 | Q11: 251 | R11: 1012 | S11: 2857 | T11: 251 | U11: 1002 | V11: 2827 | X11: =J11 -> A320 | Y11: =K11*factor16 -> 84.125686 | Z11: =L11*factor16 -> 526.83711 | AA11: =M11*factor16 -> 1918.0656 | AB11: =N11*factor16 -> 157.73566 | AC11: =O11*factor16 -> 748.7186 | AD11: =P11*factor16 -> 2371.2928 | AE11: =Q11*factor16 -> 263.94434 | AF11: =R11*factor16 -> 1064.1899 | ... AJ11: =V11*factor16 -> 2972.7914
A12: Airborne | B12: En route | C12: 179 | D12: 75 | F12: =C12*factor16 -> 188.23122 | G12: =D12*factor16 -> 78.86783 | J12: A321 | K12: 100 | L12: 581 | M12: 2165 | N12: 170 | O12: 782 | P12: 2566 | Q12: 301 | R12: 1193 | S12: 3388 | T12: 281 | U12: 1133 | V12: 3268 | X12: =J12 -> A321 | Y12: =K12*factor16 -> 105.15711 | Z12: =L12*factor16 -> 610.96279 | AA12: =M12*factor16 -> 2276.6514 | AB12: =N12*factor16 -> 178.76708 | AC12: =O12*factor16 -> 822.32858 | AD12: =P12*factor16 -> 2698.3314 | AE12: =Q12*factor16 -> 316.52289 | AF12: =R12*factor16 -> 1254.5243 | ... AJ12: =V12*factor16 -> 3436.5343
B13: (Cruise extension) | G13: =D13*factor16 -> 0 | J13: A332 | K13: 180 | L13: 992 | M13: 3559 | N13: 341 | O13: 1453 | P13: 4481 | Q13: 571 | R13: 2145 | S13: 5874 | T13: 471 | U13: 1844 | V13: 5263 | X13: =J13 -> A332 | Y13: =K13*factor16 -> 189.28279 | Z13: =L13*factor16 -> 1043.1585 | AA13: =M13*factor16 -> 3742.5414 | AB13: =N13*factor16 -> 358.58574 | AC13: =O13*factor16 -> 1527.9328 | AD13: =P13*factor16 -> 4712.09 | AE13: =Q13*factor16 -> 600.44708 | AF13: =R13*factor16 -> 2255.62 | ... AJ13: =V13*factor16 -> 5534.4186
B14: Arrival Management | C14: 174 | D14: 71 | F14: =C14*factor16 -> 182.97337 | G14: =D14*factor16 -> 74.661546 | J14: AT43 | K14: 30 | L14: 180 | M14: 611 | N14: 60 | O14: 261 | P14: 772 | Q14: 70 | R14: 291 | S14: 832 | T14: 70 | U14: 291 | V14: 832 | X14: =J14 -> AT43 | Y14: =K14*factor16 -> 31.547132 | Z14: =L14*factor16 -> 189.28279 | AA14: =M14*factor16 -> 642.50993 | AB14: =N14*factor16 -> 63.094264 | AC14: =O14*factor16 -> 274.46005 | AD14: =P14*factor16 -> 811.81287 | AE14: =Q14*factor16 -> 73.609975 | AF14: =R14*factor16 -> 306.00718 | ... AJ14: =V14*factor16 -> 874.90713
J15: AT72 | K15: 40 | L15: 241 | M15: 822 | N15: 70 | O15: 331 | P15: 1012 | Q15: 90 | R15: 391 | S15: 1133 | T15: 90 | U15: 371 | V15: 1093 | X15: =J15 -> AT72 | Y15: =K15*factor16 -> 42.062843 | Z15: =L15*factor16 -> 253.42863 | AA15: =M15*factor16 -> 864.39142 | AB15: =N15*factor16 -> 73.609975 | AC15: =O15*factor16 -> 348.07002 | AD15: =P15*factor16 -> 1064.1899 | AE15: =Q15*factor16 -> 94.641397 | AF15: =R15*factor16 -> 411.16429 | ... AJ15: =V15*factor16 -> 1149.3672
J16: B733 | K16: 70 | L16: 431 | M16: 1554 | N16: 140 | O16: 632 | P16: 1955 | Q16: 251 | R16: 962 | S16: 2626 | T16: 211 | U16: 852 | V16: 2406 | X16: =J16 -> B733 | Y16: =K16*factor16 -> 73.609975 | Z16: =L16*factor16 -> 453.22713 | AA16: =M16*factor16 -> 1634.1414 | AB16: =N16*factor16 -> 147.21995 | AC16: =O16*factor16 -> 664.59292 | AD16: =P16*factor16 -> 2055.8214 | AE16: =Q16*factor16 -> 263.94434 | AF16: =R16*factor16 -> 1011.6114 | ... AJ16: =V16*factor16 -> 2530.08
J17: B734 | K17: 80 | L17: 481 | M17: 1744 | N17: 150 | O17: 692 | P17: 2175 | Q17: 261 | R17: 1012 | S17: 2807 | T17: 251 | U17: 982 | V17: 2737 | X17: =J17 -> B734 | Y17: =K17*factor16 -> 84.125686 | Z17: =L17*factor16 -> 505.80569 | AA17: =M17*factor16 -> 1833.94 | AB17: =N17*factor16 -> 157.73566 | AC17: =O17*factor16 -> 727.68718 | AD17: =P17*factor16 -> 2287.1671 | AE17: =Q17*factor16 -> 274.46005 | AF17: =R17*factor16 -> 1064.1899 | ... AJ17: =V17*factor16 -> 2878.15
C18: 2016 values | F18: 2019 values | J18: B735 | K18: 70 | L18: 391 | M18: 1403 | N18: 140 | O18: 601 | P18: 1814 | Q18: 231 | R18: 882 | S18: 2376 | T18: 180 | U18: 742 | V18: 2095 | X18: =J18 -> B735 | Y18: =K18*factor16 -> 73.609975 | Z18: =L18*factor16 -> 411.16429 | AA18: =M18*factor16 -> 1475.3542 | AB18: =N18*factor16 -> 147.21995 | AC18: =O18*factor16 -> 631.99421 | AD18: =P18*factor16 -> 1907.5499 | AE18: =Q18*factor16 -> 242.91292 | AF18: =R18*factor16 -> 927.48569 | ... AJ18: =V18*factor16 -> 2203.0414
B19: Delay cost per minute (€) | F19: Delay cost per minute (€) | J19: B738 | K19: 90 | L19: 541 | M19: 1945 | N19: 150 | O19: 722 | P19: 2316 | Q19: 271 | R19: 1083 | S19: 3037 | T19: 251 | U19: 1022 | V19: 2917 | X19: =J19 -> B738 | Y19: =K19*factor16 -> 94.641397 | Z19: =L19*factor16 -> 568.89995 | AA19: =M19*factor16 -> 2045.3057 | AB19: =N19*factor16 -> 157.73566 | AC19: =O19*factor16 -> 759.23431 | AD19: =P19*factor16 -> 2435.4386 | AE19: =Q19*factor16 -> 284.97576 | AF19: =R19*factor16 -> 1138.8515 | ... AJ19: =V19*factor16 -> 3067.4328
A20: Ground | B20: At-Gate | C20: 15 | F20: =C20*factor16 -> 15.773566 | J20: B744 | K20: 241 | L20: 1373 | M20: 5012 | N20: 461 | O20: 2025 | P20: 6315 | Q20: 932 | R20: 3448 | S20: 9162 | T20: 712 | U20: 2767 | V20: 7799 | X20: =J20 -> B744 | Y20: =K20*factor16 -> 253.42863 | Z20: =L20*factor16 -> 1443.8071 | AA20: =M20*factor16 -> 5270.4742 | AB20: =N20*factor16 -> 484.77426 | AC20: =O20*factor16 -> 2129.4314 | AD20: =P20*factor16 -> 6640.6713 | AE20: =Q20*factor16 -> 980.06424 | AF20: =R20*factor16 -> 3625.8171 | ... AJ20: =V20*factor16 -> 8201.2028
B21: Taxi in / out | C21: 39.4 | F21: =C21*factor16 -> 41.4319 | J21: B752 | K21: 100 | L21: 621 | M21: 2295 | N21: 200 | O21: 922 | P21: 2907 | Q21: 341 | R21: 1343 | S21: 3739 | T21: 291 | U21: 1183 | V21: 3428 | X21: =J21 -> B752 | Y21: =K21*factor16 -> 105.15711 | Z21: =L21*factor16 -> 653.02564 | AA21: =M21*factor16 -> 2413.3556 | AB21: =N21*factor16 -> 210.31421 | AC21: =O21*factor16 -> 969.54853 | AD21: =P21*factor16 -> 3056.9171 | AE21: =Q21*factor16 -> 358.58574 | AF21: =R21*factor16 -> 1412.26 | ... AJ21: =V21*factor16 -> 3604.7856
A22: Airborne | B22: En-Route (Cruise extension) | C22: 70 | F22: =C22*factor16 -> 73.609975 | J22: B763 | K22: 170 | L22: 902 | M22: 3208 | N22: 291 | O22: 1263 | P22: 3929 | Q22: 511 | R22: 1925 | S22: 5253 | T22: 481 | U22: 1834 | V22: 5082 | X22: =J22 -> B763 | Y22: =K22*factor16 -> 178.76708 | Z22: =L22*factor16 -> 948.51711 | AA22: =M22*factor16 -> 3373.44 | AB22: =N22*factor16 -> 306.00718 | AC22: =O22*factor16 -> 1328.1343 | AD22: =P22*factor16 -> 4131.6227 | AE22: =Q22*factor16 -> 537.35282 | AF22: =R22*factor16 -> 2024.2743 | ... AJ22: =V22*factor16 -> 5344.0842
J23: DH8D | K23: 40 | L23: 251 | M23: 892 | N23: 70 | O23: 341 | P23: 1073 | Q23: 110 | R23: 451 | S23: 1283 | T23: 110 | U23: 451 | V23: 1283 | X23: =J23 -> DH8D | Y23: =K23*factor16 -> 42.062843 | Z23: =L23*factor16 -> 263.94434 | AA23: =M23*factor16 -> 938.0014 | AB23: =N23*factor16 -> 73.609975 | AC23: =O23*factor16 -> 358.58574 | AD23: =P23*factor16 -> 1128.3358 | AE23: =Q23*factor16 -> 115.67282 | AF23: =R23*factor16 -> 474.25855 | ... AJ23: =V23*factor16 -> 1349.1657
J24: E190 | K24: 60 | L24: 321 | M24: 1153 | N24: 110 | O24: 471 | P24: 1453 | Q24: 180 | R24: 702 | S24: 1915 | T24: 180 | U24: 692 | V24: 1885 | X24: =J24 -> E190 | Y24: =K24*factor16 -> 63.094264 | Z24: =L24*factor16 -> 337.55431 | AA24: =M24*factor16 -> 1212.4614 | AB24: =N24*factor16 -> 115.67282 | AC24: =O24*factor16 -> 495.28998 | AD24: =P24*factor16 -> 1527.9328 | AE24: =Q24*factor16 -> 189.28279 | AF24: =R24*factor16 -> 738.20289 | ... AJ24: =V24*factor16 -> 1982.2115
J28: 2016 values | X28: 2019 values
J29: Aircraft type | K29: Delay (hour) | X29: Aircraft type | Y29: Delay (mins)
K30: At-gate | L30: Taxi | M30: En route | Y30: At-gate | Z30: Taxi | AA30: En-Route
J31: A319 | K31: 812 | L31: 1925 | M31: 3428 | X31: =J31 -> A319 | Y31: =K31*factor16 -> 853.87571 | Z31: =L31*factor16 -> 2024.2743 | AA31: =M31*factor16 -> 3604.7856
J32: A320 | K32: 902 | L32: 2165 | M32: 3498 | X32: B734 | Y32: =K32*factor16 -> 948.51711 | Z32: =L32*factor16 -> 2276.6514 | AA32: =M32*factor16 -> 3678.3956
J33: A321 | K33: 1053 | L33: 2326 | M33: 4140 | X33: B735 | Y33: =K33*factor16 -> 1107.3043 | Z33: =L33*factor16 -> 2445.9543 | AA33: =M33*factor16 -> 4353.5042
J34: A332 | K34: 1724 | L34: 4250 | M34: 7237 | X34: B738 | Y34: =K34*factor16 -> 1812.9085 | Z34: =L34*factor16 -> 4469.1771 | AA34: =M34*factor16 -> 7610.2199
J35: AT43 | K35: 231 | L35: 752 | M35: 902 | X35: B752 | Y35: =K35*factor16 -> 242.91292 | Z35: =L35*factor16 -> 790.78145 | AA35: =M35*factor16 -> 948.51711
J36: AT72 | K36: 341 | L36: 982 | M36: 1273 | X36: B763 | Y36: =K36*factor16 -> 358.58574 | Z36: =L36*factor16 -> 1032.6428 | AA36: =M36*factor16 -> 1338.65
J37: B733 | K37: 541 | L37: 1714 | M37: 3208 | X37: B744 | Y37: =K37*factor16 -> 568.89995 | Z37: =L37*factor16 -> 1802.3928 | AA37: =M37*factor16 -> 3373.44
J38: B734 | K38: 601 | L38: 1874 | M38: 3298 | X38: A319 | Y38: =K38*factor16 -> 631.99421 | Z38: =L38*factor16 -> 1970.6442 | AA38: =M38*factor16 -> 3468.0814
J39: B735 | K39: 511 | L39: 1714 | M39: 2957 | X39: A320 | Y39: =K39*factor16 -> 537.35282 | Z39: =L39*factor16 -> 1802.3928 | AA39: =M39*factor16 -> 3109.4957
J40: B738 | K40: 1012 | L40: 2075 | M40: 3659 | X40: A321 | Y40: =K40*factor16 -> 1064.1899 | Z40: =L40*factor16 -> 2182.01 | AA40: =M40*factor16 -> 3847.6986
J41: B744 | K41: 1504 | L41: 4972 | M41: 10976 | X41: AT43 | Y41: =K41*factor16 -> 1581.5629 | Z41: =L41*factor16 -> 5228.4114 | AA41: =M41*factor16 -> 11542.044
J42: B752 | K42: 722 | L42: 2396 | M42: 4220 | X42: AT72 | Y42: =K42*factor16 -> 759.23431 | Z42: =L42*factor16 -> 2519.5643 | AA42: =M42*factor16 -> 4437.6299
J43: B763 | K43: 1313 | L43: 3388 | M43: 6245 | X43: DH8D | Y43: =K43*factor16 -> 1380.7128 | Z43: =L43*factor16 -> 3562.7228 | AA43: =M43*factor16 -> 6567.0613
... J45: E190 | K45: 772 | L45: 1724 | M45: 2757 | X45: A332 | Y45: =K45*factor16 -> 811.81287 | Z45: =L45*factor16 -> 1812.9085 | AA45: =M45*factor16 -> 2899.1814

Sheet Passenger time value
A1: Passenger value of time
A3: Value [1]: | B3: € 40 - € 52 per hour per passenger (Adjusted from 1999 prices) | F3: =F22 -> 49.605184 | G3: =G22 -> 63.533733
A5: Value [1] (adjusted from 1999 prices):
B6: Private Travel | C6: Business Travel
A7: Travel time | B7: 23.8 | C7: 30.1 | F7: =B7*factor99 -> 34.210472 | G7: =C7*factor99 -> 43.266185
A8: Waiting time between departures | B8: 2.7 | C8: 10.2 | F8: =B8*factor99 -> 3.8810199 | G8: =C8*factor99 -> 14.661631
A10: Value [3]:
B11: Air Carrier | C11: General Aviation
A12: Personal | B12: 17.9 | C12: 24.2 | F12: =F27*dollar -> #REF! | G12: =G27*dollar -> #REF!
A13: Business | B13: 31.7 | C13: 34.5 | F13: =F28*dollar -> #REF! | G13: =G28*dollar -> #REF!
A14: All purposes | B14: 24.6 | C14: 28.6 | F14: =F29*dollar -> #REF! | G14: =G29*dollar -> #REF!
A16: Source [1]:
B17: VOT per hour (€)
A18: Purpose | B18: Low | C18: High
A19: Business | B19: 47 | C19: 63 | E19: 0.49 | F19: =B19*factor99 -> 67.558495 | G19: =C19*factor99 -> 90.557131
A20: Personal convenience | B20: 28 | C20: 33 | E20: 0.16 | F20: =B20*factor99 -> 40.247614 | G20: =C20*factor99 -> 47.434688
A21: Tourism | B21: 20 | C21: 23 | E21: 0.35 | F21: =B21*factor99 -> 28.748296 | G21: =C21*factor99 -> 33.06054
A22: Average | B22: 34 | C22: 44 | F22: {=SUM(E19:E21*F19:F21)} -> 49.605184 | G22: {=SUM(E19:E21*G19:G21)} -> 63.533733
A24: Value [2] (adjusted from 1998 prices)
B25: Air Carrier | C25: General Aviation
B26: (cost per hour) | C26: (cost per hour)
A27: Personal | B27: 19.5 | C27: 26.3 | F27: =B27*factor98 -> 28.362169 | G27: =C27*factor98 -> 38.252566 | I27: =F27/#REF! -> #REF! | J27: =G27/#REF! -> #REF!
A28: Business | B28: 34.5 | C28: 37.5 | F28: =B28*factor98 -> 50.179222 | G28: =C28*factor98 -> 54.542632 | I28: =F28/#REF! -> #REF! | J28: =G28/#REF! -> #REF!
A29: All purposes | B29: 26.7 | C29: 31.1 | F29: =B29*factor98 -> 38.834354 | G29: =C29*factor98 -> 45.234023 | I29: =F29/#REF! -> #REF! | J29: =G29/#REF! -> #REF!
A32: Vilma Deltuvaitė/ORO NAVIGACIJA (ON (B4)) deltuvaite.v@ans.lt
A35: Value [1]:
A36: 2002 | G36: 2019
A37: Per Hour | B37: Air Carrier | F37: Air Carrier
A38: Personal[1] | B38: 10.61 | C38: 16.25 | F38: =B38*factor02 -> 14.347181 | G38: =C38*factor02 -> 21.973769
A39: Business | B39: 32.8 | F39: =B39*factor02 -> 44.353207
A44: Value [3]:
A45: in 2015€ | C45: in FR €2019
A46: Per Hour[1] | B46: Air Carrier | C46: Air Carrier
A47: Personal-holiday | B47: 55.5 | C47: =B47*FR_factor15 -> 58.24725
A48: Personal-other | B48: 56.8 | C48: =B48*FR_factor15 -> 59.6116
A49: Business | B49: 77.5 | C49: =B49*FR_factor15 -> 81.33625
A50: All purposes | B50: 57.7 | C50: =B50*FR_factor15 -> 60.55615
A53: Values of time used to estimate passenger delay costs in the UK airport system (2014) Airports Commission – Economy: Delay Impacts Assessment Methodology Paper
A54: https://assets.publishing.service.gov.uk/government/uploads/system/uploads/attachment_data/file/372606/AC08a_tagged.pdf
B56: `£ 2014 | C56: £ 2019 | D56: 2019
A57: Per Hour | B57: Air Carrier | C57: Air Carrier | D57: Air Carrier
A58: Leisure | B58: 6.6 | C58: =B58*UK_factor14 -> 7.1148 | D58: =C58/ExR_GBP_19 -> 8.1055402
A59: UK Business | B59: 49.2 | C59: =B59*UK_factor14 -> 53.0376 | D59: =C59/ExR_GBP_19 -> 60.423118
A60: Foreign Business | B60: 46.8 | C60: =B60*UK_factor14 -> 50.4504 | D60: =C60/ExR_GBP_19 -> 57.475649
A63: Values of travel time in Europe: Review and meta-analysis – University of Leeds (2016) - Table 9
A64: http://eprints.whiterose.ac.uk/104595/1/European meta paper final accepted for publication.pdf
B66: 2010 | C66: 2019
A67: Country | B67: Air Employer’s Business (EB) | C67: Air Employer’s Business (EB)
A68: France | B68: 49.3 | C68: =B68*factor10 -> 56.192086
A69: Germany | B69: 54.6 | C69: =B69*factor10 -> 62.23302
A70: Italy | B70: 45.8 | C70: =B70*factor10 -> 52.202789
A71: Spain | B71: 45.7 | C71: =B71*factor10 -> 52.08881
A72: UK | B72: 51.8 | C72: =B72*factor10 -> 59.041583
A75: Value 2
A77: U.S. Department of Transportation
A78: in 2015 US$ | C78: US inflation to 2016 | D78: in 2019 €
D79: ='basic assumptions'!H9 -> 1.1069
A80: US$ 2015 / hour | B80: Air Carrier | C80: Air Carrier | D80: Air Carrier | H80: € / hour | I80: Air Carrier
A81: Personal | B81: 36.1 | C81: =B81*US_factor15 -> 38.939054 | D81: =C81*'basic assumptions'!$H$12 -> 43.592271 | H81: Personal | I81: US $ 34.2 (€ 30.9)
A82: Business | B82: 63.2 | C82: =B82*US_factor15 -> 68.17031 | D82: =C82*'basic assumptions'!$H$12 -> 76.316662 | H82: Business | I82: US $ 62.5 (€ 56.5)
A83: All purposes | B83: 47.1 | C83: =B83*US_factor15 -> 50.804139 | D83: =C83*'basic assumptions'!$H$12 -> 56.875234 | H83: All purposes | I83: US $ 45.6 (€ 41.2)

Sheet VSL
A1: VSL
A4: European Commission (2009), “Part III: Annexes to Impact Assessment Guidelines”, 15 January 2009 | G4: “Handbook on the external costs of transport”, CE Delft, January 2019 (commissioned by European Union DG Move)
A5: https://ec.europa.eu/smart-regulation/impact/commission_guidelines/docs/iag_2009_annex_en.pdf | G5: https://www.cedelft.eu/en/publications/2311/handbook-on-the-external-costs-of-transport-version-2019
B8: 2004 | D8: 2019 | H8: 2004 | I8: 2019
A9: Median | B9: 980000 | D9: =B9*factor04 -> 1274036.3 | G9: EU28 average | H9: 2900000 | I9: =H9*factor16 -> 3049556.1
A10: Mean | B10: 2000000 | D10: =B10*factor04 -> 2600074

Sheet Cost of noise
A2: Environmental price of aviation traffic noise for the EU28 for different noise levels
A3: “Handbook on the external costs of transport”, CE Delft, January 2019 (commissioned by European Union DG Move), tables 33 and 36
A4: https://ec.europa.eu/transport/sites/transport/files/studies/internalisation-handbook-isbn-978-92-79-96917-1.pdf
A6: (EU28 in €2016 per person per dB, Lden | H6: in €2019
A7: Noise levels Lden in dB(A | B7: Annoyance | C7: Health | D7: Total | H7: Noise levels Lden in dB(A | I7: Annoyance | J7: Health | K7: Total
A8: 50‑54 | B8: 34 | C8: 5 | D8: 39 | H8: 50‑54 | I8: =B8*factor16 -> 35.753416 | J8: =C8*factor16 -> 5.2578554 | K8: =D8*factor16 -> 41.011272
A9: 55‑59 | B9: 68 | C9: 6 | D9: 74 | H9: 55‑59 | I9: =B9*factor16 -> 71.506833 | J9: =C9*factor16 -> 6.3094264 | K9: =D9*factor16 -> 77.816259
A10: 60‑64 | B10: 68 | C10: 9 | D10: 77 | H10: 60‑64 | I10: =B10*factor16 -> 71.506833 | J10: =C10*factor16 -> 9.4641397 | K10: =D10*factor16 -> 80.970973
A11: 65‑69 | B11: 129 | C11: 12 | D11: 141 | H11: 65‑69 | I11: =B11*factor16 -> 135.65267 | J11: =C11*factor16 -> 12.618853 | K11: =D11*factor16 -> 148.27152
A12: 70‑74 | B12: 129 | C12: 16 | D12: 145 | H12: 70‑74 | I12: =B12*factor16 -> 135.65267 | J12: =C12*factor16 -> 16.825137 | K12: =D12*factor16 -> 152.47781
A13: ≥ 75 | B13: 129 | C13: 21 | D13: 150 | H13: ≥ 75 | I13: =B13*factor16 -> 135.65267 | J13: =C13*factor16 -> 22.082993 | K13: =D13*factor16 -> 157.73566
H16: in €2019
B17: Total Costs | C17: Average Costs | I17: Total Costs | J17: Average Costs
B18: Billion € | C18: €/LTO | D18: €/pax[1] | E18: €/tonne | F18: €cent /km | I18: Billion € | J18: €/LTO | K18: €/pax[1] | L18: €/tonne | M18: €cent /km
A19: Short haul | B19: 0.84 | C19: 257 | D19: 2.05 | E19: 9.04 | F19: 0.46 | H19: Short haul | I19: =B19*factor16 -> 0.8833197 | J19: =C19*factor16 -> 270.25377 | K19: =D19*factor16 -> 2.1557207 | L19: =E19*factor16 -> 9.5062025 | M19: =F19*factor16 -> 0.48372269
A20: Medium haul | F20: 0.11 | H20: Medium haul | M20: =F20*factor16 -> 0.11567282
A21: Long haul | F21: 0.01 | H21: Long haul | M21: =F21*factor16 -> 0.010515711
A24: [1] Costs per pax are including the complete flight (not only the half-way principle).
S26: MD82 | T26: =T88*$T$92 -> 110.7
A28: 2014 values: https://www.gov.uk/guidance/noise-pollution-economic-analysis
L30: 2019 values
A31: Change in noise metric by decibel (Db) (daytime noise metric) | C31: Total Aircraft (excluding sleep disturbance GBP 2014) | D31: Total Aircraft (excluding sleep disturbance GBP 2019) | E31: Total Aircraft (excluding sleep disturbance EUR€ 2019) | F31: Aviation sleep disturbance (GBP 2014) | G31: sleep disturbance GBP 2019 | H31: sleep disturbance EUR€ 2019 | J31: Change in noise metric by decibel (Db) (daytime noise metric) | L31: Total Aircraft (excluding sleep disturbance) in€ (2019 prices) | M31: Sleep disturbance) in€ (2019 prices)
A33: 45 | B33: 46 | C33: 15.614324 | D33: =C33*UK_factor14 -> 16.832241 | E33: =D33/ExR_GBP_19 -> 19.176141 | F33: 37.927092 | G33: =F33*UK_factor14 -> 40.885405 | H33: =G33/ExR_GBP_19 -> 46.578722 | J33: 45 | K33: 46 | L33: =E33 -> 19.176141 | M33: =H33 -> 46.578722
A34: 46 | B34: 47 | C34: 17.723854 | D34: =C34*UK_factor14 -> 19.106314 | E34: =D34/ExR_GBP_19 -> 21.76688 | F34: 40.790316 | G34: =F34*UK_factor14 -> 43.971961 | H34: =G34/ExR_GBP_19 -> 50.095083 | J34: 50 | K34: 51 | L34: =E38 -> 47.542635 | M34: =H38 -> 64.160523
A35: 47 | B35: 48 | C35: 19.81815 | D35: =C35*UK_factor14 -> 21.363966 | E35: =D35/ExR_GBP_19 -> 24.338911 | F35: 43.65354 | G35: =F35*UK_factor14 -> 47.058516 | H35: =G35/ExR_GBP_19 -> 53.611443 | J35: 55 | K35: 56 | L35: =E43 -> 60.1897 | M35: =H43 -> 81.742324
A36: 48 | B36: 49 | C36: 21.897213 | D36: =C36*UK_factor14 -> 23.605195 | E36: =D36/ExR_GBP_19 -> 26.892233 | F36: 46.516764 | G36: =F36*UK_factor14 -> 50.145072 | H36: =G36/ExR_GBP_19 -> 57.127803 | J36: 60 | K36: 61 | L36: =E48 -> 77.72285 | M36: =H48 -> 99.324125
A37: 49 | B37: 50 | C37: 23.961042 | D37: =C37*UK_factor14 -> 25.830003 | E37: =D37/ExR_GBP_19 -> 29.426847 | F37: 49.379988 | G37: =F37*UK_factor14 -> 53.231627 | H37: =G37/ExR_GBP_19 -> 60.644163 | J37: 65 | K37: 66 | L37: =E53 -> 98.033169 | M37: =H53 -> 116.90593
A38: 50 | B38: 51 | C38: 38.711966 | D38: =C38*UK_factor14 -> 41.731499 | E38: =D38/ExR_GBP_19 -> 47.542635 | F38: 52.243212 | G38: =F38*UK_factor14 -> 56.318183 | H38: =G38/ExR_GBP_19 -> 64.160523 | J38: 70 | K38: 71 | L38: =E58 -> 119.101 | M38: =H58 -> 116.90593
A39: 51 | B39: 52 | C39: 40.801481 | D39: =C39*UK_factor14 -> 43.983996 | E39: =D39/ExR_GBP_19 -> 50.108794 | F39: 55.106436 | G39: =F39*UK_factor14 -> 59.404738 | H39: =G39/ExR_GBP_19 -> 67.676883 | J39: 75 | K39: 76 | L39: =E63 -> 140.92658 | M39: =H63 -> 116.90593
A40: 52 | B40: 53 | C40: 42.876034 | D40: =C40*UK_factor14 -> 46.220365 | E40: =D40/ExR_GBP_19 -> 52.656578 | F40: 57.96966 | G40: =F40*UK_factor14 -> 62.491293 | H40: =G40/ExR_GBP_19 -> 71.193244 | J40: 80 | K40: 81 | L40: =E68 -> 153.15664 | M40: =H68 -> 116.90593
A41: 53 | B41: 54 | C41: 44.935627 | D41: =C41*UK_factor14 -> 48.440606 | E41: =D41/ExR_GBP_19 -> 55.185989 | F41: 60.832884 | G41: =F41*UK_factor14 -> 65.577849 | H41: =G41/ExR_GBP_19 -> 74.709604
A42: 54 | B42: 55 | C42: 46.980261 | D42: =C42*UK_factor14 -> 50.644722 | E42: =D42/ExR_GBP_19 -> 57.69703 | F42: 63.696108 | G42: =F42*UK_factor14 -> 68.664404 | H42: =G42/ExR_GBP_19 -> 78.225964
A43: 55 | B43: 56 | C43: 49.009938 | D43: =C43*UK_factor14 -> 52.832713 | E43: =D43/ExR_GBP_19 -> 60.1897 | F43: 66.559332 | G43: =F43*UK_factor14 -> 71.75096 | H43: =G43/ExR_GBP_19 -> 81.742324
A44: 56 | B44: 57 | C44: 51.024659 | D44: =C44*UK_factor14 -> 55.004583 | E44: =D44/ExR_GBP_19 -> 62.664004 | F44: 69.422556 | G44: =F44*UK_factor14 -> 74.837515 | H44: =G44/ExR_GBP_19 -> 85.258684
A45: 57 | B45: 58 | C45: 53.024426 | D45: =C45*UK_factor14 -> 57.160331 | E45: =D45/ExR_GBP_19 -> 65.119942 | F45: 72.28578 | G45: =F45*UK_factor14 -> 77.924071 | H45: =G45/ExR_GBP_19 -> 88.775045
A46: 58 | B46: 59 | C46: 56.563911 | D46: =C46*UK_factor14 -> 60.975896 | E46: =D46/ExR_GBP_19 -> 69.466826 | F46: 75.149004 | G46: =F46*UK_factor14 -> 81.010626 | H46: =G46/ExR_GBP_19 -> 92.291405
A47: 59 | B47: 60 | C47: 60.052875 | D47: =C47*UK_factor14 -> 64.736999 | E47: =D47/ExR_GBP_19 -> 73.751666 | F47: 78.012228 | G47: =F47*UK_factor14 -> 84.097182 | H47: =G47/ExR_GBP_19 -> 95.807765
A48: 60 | B48: 61 | C48: 63.286443 | D48: =C48*UK_factor14 -> 68.222786 | E48: =D48/ExR_GBP_19 -> 77.72285 | F48: 80.875452 | G48: =F48*UK_factor14 -> 87.183737 | H48: =G48/ExR_GBP_19 -> 99.324125
A49: 61 | B49: 62 | C49: 66.544676 | D49: =C49*UK_factor14 -> 71.73516 | E49: =D49/ExR_GBP_19 -> 81.724325 | F49: 83.738676 | G49: =F49*UK_factor14 -> 90.270293 | H49: =G49/ExR_GBP_19 -> 102.84049
A50: 62 | B50: 63 | C50: 69.827574 | D50: =C50*UK_factor14 -> 75.274125 | E50: =D50/ExR_GBP_19 -> 85.756092 | F50: 86.6019 | G50: =F50*UK_factor14 -> 93.356848 | H50: =G50/ExR_GBP_19 -> 106.35685
A51: 63 | B51: 64 | C51: 73.13514 | D51: =C51*UK_factor14 -> 78.839681 | E51: =D51/ExR_GBP_19 -> 89.818154 | F51: 89.465124 | G51: =F51*UK_factor14 -> 96.443404 | H51: =G51/ExR_GBP_19 -> 109.87321
A52: 64 | B52: 65 | C52: 76.467375 | D52: =C52*UK_factor14 -> 82.431831 | E52: =D52/ExR_GBP_19 -> 93.910513 | F52: 92.328348 | G52: =F52*UK_factor14 -> 99.529959 | H52: =G52/ExR_GBP_19 -> 113.38957
... A68: 80 | B68: 81 | C68: 124.709 | D68: =C68*UK_factor14 -> 134.4363 | E68: =D68/ExR_GBP_19 -> 153.15664 | F68: 95.191572 | G68: =F68*UK_factor14 -> 102.61651 | H68: =G68/ExR_GBP_19 -> 116.90593
A75: 2008 values | C75: http://www.cedelft.eu/publicatie/external_costs_of_transport_in_europe/1258
J76: 2001 €/landing | L76: https://dspace.lib.cranfield.ac.uk/bitstream/1826/3151/1/Determination%20and%20Applications%20of%20Environmental%20Costs%20at%20Different%20Sized%20Airports-2006.pdf
A77: Country | B77: Noise levels Lden in dB(A)
B78: 55-59 | C78: 60-64 | D78: 65-69 | E78: 70-74 | F78: 75-79 | J78: Cat. | K78: Aircraft Type | L78: Heathrow | M78: Schiphol | N78: Gatwick | O78: Stansted | P78: Maastricht | S78: from £2000 to £2007
A79: France | B79: 120 | C79: 205 | D79: 291 | E79: 429 | F79: 558 | J79: 1 | K79: Jetstream 31 | L79: 28 | M79: 14 | N79: 1 | O79: 1 | P79: 14
A80: Germany | B80: 110 | C80: 188 | D80: 266 | E80: 394 | F80: 513 | J80: 2 | K80: B737-300 | L80: 510 | M80: 265 | N80: 19 | O80: 11 | P80: 259 | S80: Aircraft Type | T80: Marginal Damage Costs (€) | Y80: £
A81: Italy | B81: 113 | C81: 194 | D81: 275 | E81: 406 | F81: 529 | J81: 3 | K81: A310-203 | L81: 831 | M81: 431 | N81: 31 | O81: 17 | P81: 422 | S81: A 310 | T81: 63
A82: Spain | B82: 117 | C82: 200 | D82: 283 | E82: 414 | F82: 537 | J82: 4 | K82: B747-400 | L82: 1975 | M82: 1024 | N82: 74 | O82: 41 | P82: 1003 | S82: A 340 | T82: 142
A83: United Kingdom | B83: 125 | C83: 214 | D83: 303 | E83: 447 | F83: 582 | J83: 5 | K83: B747-100F/200/300 | L83: 3007 | M83: 1560 | N83: 113 | O83: 63 | P83: 1528 | S83: B 737-400 | T83: 63
J84: 6 | K84: B737-200QN | L84: 2035 | M84: 1056 | N84: 76 | O84: 43 | P84: 1034 | S84: B 747-400 | T84: 311
J85: 7 | K85: B727 | L85: 2194 | M85: 1138 | N85: 82 | O85: 46 | P85: 1115 | S85: B 757 | T85: 82
S86: B 767-300 | T86: 100
S87: B 777 | T87: 61
A88: indexed | B88: from 2008 | S88: MD82 | T88: 90
J89: indexed from
A90: Country | B90: Noise levels Lden in dB(A)
B91: 55-59 | C91: 60-64 | D91: 65-69 | E91: 70-74 | F91: 75-79 | J91: Cat. | K91: Aircraft Type | L91: Heathrow | M91: Schiphol | N91: Gatwick | O91: Stansted | P91: Maastricht | S91: from £2007 to £2014
A92: France | B92: =B79*FR_factor10 -> 133.9075 | C92: =C79*FR_factor10 -> 228.75864 | D92: =D79*FR_factor10 -> 324.72568 | E92: =E79*FR_factor10 -> 478.7193 | F92: =F79*FR_factor10 -> 622.66986 | J92: 1 | K92: Jetstream 31 | L92: =L79*factor01 -> 38.650779 | M92: =M79*factor01 -> 19.32539 | N92: =N79*factor01 -> 1.380385 | O92: =O79*factor01 -> 1.380385 | P92: =P79*factor01 -> 19.32539 | S92: 1£ = | T92: 1.23
A93: Germany | B93: =B80*DE_factor08 -> 126.96937 | C93: =C80*DE_factor08 -> 217.00219 | D93: =D80*DE_factor08 -> 307.03501 | E93: =E80*DE_factor08 -> 454.78118 | F93: =F80*DE_factor08 -> 592.13895 | J93: 2 | K93: B737-300 | L93: =L80*factor01 -> 703.99633 | M93: =M80*factor01 -> 365.80202 | N93: =N80*factor01 -> 26.227314 | O93: =O80*factor01 -> 15.184235 | P93: =P80*factor01 -> 357.51971 | S93: Aircraft Type | T93: Marginal Damage Costs (€)
A94: Italy | B94: =B81*IT_factor08 -> 129 | C94: =C81*IT_factor08 -> 221.46903 | D94: =D81*IT_factor08 -> 313.93805 | E94: =E81*IT_factor08 -> 463.48673 | F94: =F81*IT_factor08 -> 603.90265 | J94: 3 | K94: A310-203 | L94: =L81*factor01 -> 1147.0999 | M94: =M81*factor01 -> 594.94592 | N94: =N81*factor01 -> 42.791934 | O94: =O81*factor01 -> 23.466544 | P94: =P81*factor01 -> 582.52246 | S94: A310 | T94: =T81*$T$92 -> 77.49
A95: Spain | B95: =B82*SP_factor08 -> 132.00325 | C95: =C82*SP_factor08 -> 225.64658 | D95: =D82*SP_factor08 -> 319.2899 | E95: =E82*SP_factor08 -> 467.08841 | F95: =F82*SP_factor08 -> 605.86105 | J95: 4 | K95: B747-400 | L95: =L82*factor01 -> 2726.2603 | M95: =M82*factor01 -> 1413.5142 | N95: =N82*factor01 -> 102.14849 | O95: =O82*factor01 -> 56.595784 | P95: =P82*factor01 -> 1384.5261 | S95: A340 | T95: =T82*$T$92 -> 174.66
A96: United Kingdom | B96: =B83*UK_factor08 -> 159.09091 | C96: =C83*UK_factor08 -> 272.36364 | D96: =D83*UK_factor08 -> 385.63636 | E96: =E83*UK_factor08 -> 568.90909 | F96: =F83*UK_factor08 -> 740.72727 | J96: 5 | K96: B747-100F/200/300 | L96: =L83*factor01 -> 4150.8176 | M96: =M83*factor01 -> 2153.4005 | N96: =N83*factor01 -> 155.9835 | O96: =O83*factor01 -> 86.964253 | P96: =P83*factor01 -> 2109.2282 | S96: B737-400 | T96: =T83*$T$92 -> 77.49
J97: 6 | K97: B737-200QN | L97: =L84*factor01 -> 2809.0834 | M97: =M84*factor01 -> 1457.6865 | N97: =N84*factor01 -> 104.90926 | O97: =O84*factor01 -> 59.356554 | P97: =P84*factor01 -> 1427.3181 | S97: B747-400 | T97: =T84*$T$92 -> 382.53
J98: 7 | K98: B727 | L98: =L85*factor01 -> 3028.5646 | M98: =M85*factor01 -> 1570.8781 | N98: =N85*factor01 -> 113.19157 | O98: =O85*factor01 -> 63.497709 | P98: =P85*factor01 -> 1539.1292 | S98: B757 | T98: =T85*$T$92 -> 100.86
S99: B767-300 | T99: =T86*$T$92 -> 123
S100: B777 | T100: =T87*$T$92 -> 75.03

Sheet cost of pollutant
A3: “Handbook on the external costs of transport”, CE Delft, January 2019 (commissioned by European Union DG Move), tables 33 and 36
A4: https://ec.europa.eu/transport/sites/transport/files/studies/internalisation-handbook-isbn-978-92-79-96917-1.pdf
E7: 2016 | N7: 2019
A8: Distance group | B8: Range | C8: €’000/year | D8: € cent/km | E8: € cent/pax (complete flight) | J8: Distance group | K8: Range | L8: €’000/year | M8: € cent/km | N8: € cent/pax (complete flight)
A10: Short-haul | B10: < 1 500 km | C10: 270 | D10: 0.3 | E10: 163 | J10: Short-haul | K10: < 1 500 km | L10: =C10*factor16 -> 283.92419 | M10: =D10*factor16 -> 0.31547132 | N10: =E10*factor16 -> 171.40608
A11: Medium-haul | B11: < 1 500-5 000 km | C11: 380 | D11: 0.13 | E11: 231 | J11: Medium-haul | K11: < 1 500-5 000 km | L11: =C11*factor16 -> 399.59701 | M11: =D11*factor16 -> 0.13670424 | N11: =E11*factor16 -> 242.91292
A12: Long-haul | B12: > 5 000 km | C12: 360 | D12: 0.06 | E12: 444 | J12: Long-haul | K12: > 5 000 km | L12: =C12*factor16 -> 378.56559 | M12: =D12*factor16 -> 0.063094264 | N12: =E12*factor16 -> 466.89756
A13: Total | C13: 1010 | D13: 0.1 | E13: 246 | J13: Total | L13: =C13*factor16 -> 1062.0868 | M13: =D13*factor16 -> 0.10515711 | N13: =E13*factor16 -> 258.68648
G17: 2016 | P17: 2019
A18: Type of flight | B18: Distance [km] | C18: Emission class | D18: Example of aircraft type | E18: € per LTO* | F18: €-cent per pkm* | G18: € per pax* | J18: Type of flight | K18: Distance [km] | L18: Emission class | M18: Example of aircraft type | N18: € per LTO* | O18: €-cent per pkm* | P18: € per pax*
A19: Short haul | B19: 500 | C19: Low | D19: Bombardier CRJ900 | E19: 101 | F19: 0.28 | G19: 1.42 | J19: Short haul | K19: 500 | L19: Low | M19: Bombardier CRJ900 | N19: =E19*factor16 -> 106.20868 | O19: =F19*factor16 -> 0.2944399 | P19: =G19*factor16 -> 1.4932309
B20: 500 | C20: High | D20: Embraer 170 | E20: 137 | F20: 0.3 | G20: 1.52 | K20: 500 | L20: High | M20: Embraer 170 | N20: =E20*factor16 -> 144.06524 | O20: =F20*factor16 -> 0.31547132 | P20: =G20*factor16 -> 1.598388
A21: Medium haul | B21: 1500 | C21: Low | D21: Airbus 320 | E21: 165 | F21: 0.07 | G21: 1.11 | J21: Medium haul | K21: 1500 | L21: Low | M21: Airbus 320 | N21: =E21*factor16 -> 173.50923 | O21: =F21*factor16 -> 0.073609975 | P21: =G21*factor16 -> 1.1672439
B22: 1500 | C22: High | D22: Boeing 737 | E22: 185 | F22: 0.11 | G22: 1.58 | K22: 1500 | L22: High | M22: Boeing 737 | N22: =E22*factor16 -> 194.54065 | O22: =F22*factor16 -> 0.11567282 | P22: =G22*factor16 -> 1.6614823
B23: 3000 | C23: Low | D23: Airbus 320 | E23: 219 | F23: 0.05 | G23: 1.47 | K23: 3000 | L23: Low | M23: Airbus 320 | N23: =E23*factor16 -> 230.29406 | O23: =F23*factor16 -> 0.052578554 | P23: =G23*factor16 -> 1.5458095
B24: 3000 | C24: High | D24: Boeing 737 | E24: 245 | F24: 0.07 | G24: 2.09 | K24: 3000 | L24: High | M24: Boeing 737 | N24: =E24*factor16 -> 257.63491 | O24: =F24*factor16 -> 0.073609975 | P24: =G24*factor16 -> 2.1977835
A25: Long haul | B25: 5000 | C25: Low | D25: Airbus 340 | E25: 502 | F25: 0.03 | G25: 1.7 | J25: Long haul | K25: 5000 | L25: Low | M25: Airbus 340 | N25: =E25*factor16 -> 527.88868 | O25: =F25*factor16 -> 0.031547132 | P25: =G25*factor16 -> 1.7876708
B26: 5000 | C26: High | D26: Boeing 777 | E26: 833 | F26: 0.04 | G26: 1.92 | K26: 5000 | L26: High | M26: Boeing 777 | N26: =E26*factor16 -> 875.9587 | O26: =F26*factor16 -> 0.042062843 | P26: =G26*factor16 -> 2.0190165
B27: 15000 | C27: Low | D27: Airbus 340 | E27: 711 | F27: 0.02 | G27: 2.41 | K27: 15000 | L27: Low | M27: Airbus 340 | N27: =E27*factor16 -> 747.66703 | O27: =F27*factor16 -> 0.021031421 | P27: =G27*factor16 -> 2.5342863
B28: 15000 | C28: High | D28: Boeing 777 | E28: 1.179 | F28: 0.02 | G28: 2.72 | K28: 15000 | L28: High | M28: Boeing 777 | N28: =E28*factor16 -> 1.2398023 | O28: =F28*factor16 -> 0.021031421 | P28: =G28*factor16 -> 2.8602733
C31: 2016 | G31: 2019
A32: Forecast | B32: Low[1] | C32: Medium | D32: High | F32: Low[1] | G32: Medium | H32: High
A33: Short-and-medium-run (up to 2030) | B33: 60 | C33: 100 | D33: 189 | F33: =B33*factor16 -> 63.094264 | G33: =C33*factor16 -> 105.15711 | H33: =D33*factor16 -> 198.74693
A34: Long run (from 2040 to 2060) | B34: 156 | C34: 269 | D34: 498 | F34: =B34*factor16 -> 164.04509 | G34: =C34*factor16 -> 282.87262 | H34: =D34*factor16 -> 523.68239
E37: 2016 | J37: 2019
A38: Costs in € per kg | B38: NOx | C38: NMVOC | D38: SO2 | E38: PM2.5 (exhaust) | G38: NOx | H38: NMVOC | I38: SO2 | J38: PM2.5 (exhaust)
A39: EU-27+UK | B39: 10.9 | C39: 1.2 | D39: 10.9 | E39: 19.4 | G39: =B39*factor16 -> 11.462125 | H39: =C39*factor16 -> 1.2618853 | I39: =D39*factor16 -> 11.462125 | J39: =E39*factor16 -> 20.400479
E45: in Pounds | F45: 2017 | L45: in EURO | M45: 2017 | P45: rounded | Q45: in EURO | R45: 2017
C46: Pollutant Emitted Aircraft | D46: Central Damage Cost (£/t) | E46: Low – high damage cost sensitivity range (£/t) | J46: Pollutant Emitted Aircraft | K46: Central Damage Cost (£/t) | L46: Low – high damage cost sensitivity range (£/t) | O46: Pollutant Emitted Aircraft | P46: Central Damage Cost (£/t) | Q46: Low – high damage cost sensitivity range (£/t)
E47: Low (£/t) | F47: High (£/t) | L47: Low (£/t) | M47: High (£/t) | Q47: Low (£/t) | R47: High (£/t)
C48: PM2.5 | D48: 194269 | E48: 40571 | F48: 560317 | J48: PM2.5 | K48: =D48/'basic assumptions'!I10 -> 221598.78 | L48: =E48/'basic assumptions'!I10 -> 46278.531 | M48: =F48/'basic assumptions'!I10 -> 639142.44 | O48: PM2.5 | P48: =ROUNDUP(K48,-2) -> 221600 | Q48: =ROUNDUP(L48,-2) -> 46300 | R48: =ROUNDUP(M48,-2) -> 639200
C49: NOx | D49: 11672 | E49: 1054 | F49: 44732 | J49: NOx | K49: =D49/'basic assumptions'!$I$10 -> 13314.018 | L49: =E49/'basic assumptions'!$I$10 -> 1202.2768 | M49: =F49/'basic assumptions'!$I$10 -> 51024.901 | O49: NOx | P49: =ROUNDUP(K49,-2) -> 13400 | Q49: =ROUNDUP(L49,-2) -> 1300 | R49: =ROUNDUP(M49,-2) -> 51100
E52: in Pounds | F52: 2017 | L52: in Pounds | M52: 2017
C53: Pollutant Emitted Aircraft | D53: Central Damage Cost (£/t) | E53: Low – high damage cost sensitivity range (£/t) | J53: Pollutant Emitted Aircraft | K53: Central Damage Cost (£/t) | L53: Low – high damage cost sensitivity range (£/t)
E54: Low (£/t) | F54: High (£/t) | L54: Low (£/t) | M54: High (£/t)
C55: PM2.5 | D55: =D48/1000 -> 194.269 | E55: =E48/1000 -> 40.571 | F55: =F48/1000 -> 560.317 | J55: PM2.5 | K55: =K48/1000 -> 221.59878 | L55: =L48/1000 -> 46.278531 | M55: =M48/1000 -> 639.14244
C56: NOx | D56: =D49/1000 -> 11.672 | E56: =E49/1000 -> 1.054 | F56: =F49/1000 -> 44.732 | J56: NOx | K56: =K49/1000 -> 13.314018 | L56: =L49/1000 -> 1.2022768 | M56: =M49/1000 -> 51.024901

Sheet Average Pass Flight
C2: 2011 | F2: 2014 | I2: 2019
C3: International flight[1] | D3: Domestic flight | F3: International flight[1] | G3: Domestic flight | I3: International flight[1] | J3: Domestic flight
B4: Consumer benefits per flight | C4: 24222 | D4: 4444 | F4: 25373.858 | G4: 4655.3309 | I4: =C4*factor11 -> 26777.299 | J4: =D4*factor11 -> 4912.8196
B5: Airline benefits per flight (excluding fuel and labour) | C5: 727 | D5: 131 | F5: 761.57191 | G5: 168.65623 | I5: =C5*factor11 -> 803.69484 | J5: =D5*factor11 -> 144.81984
B6: Other producer benefits[2] per flight (excluding fuel and labour) | C6: 1309 | D6: 648 | F6: 1371.2485 | G6: 678.81513 | I6: =C6*factor11 -> 1447.0929 | J6: =D6*factor11 -> 716.36074
B7: Wider economic | C7: For a 10% rise in connectivity, long term labour productivity levels improved by 0.07% | F7: For a 10% rise in connectivity, long term labour productivity levels improved by 0.07% | I7: For a 10% rise in connectivity, long term labour productivity levels improved by 0.07%
B10: [1] “International passengers include all departing international passengers from each member State and inbound passengers from non‑EU countries, with only origin‑destination passengers counted. Passengers transiting through the EU, with origins and destinations outside the EU, are not taken into account in this analysis. Flights between member States (between Germany and France) are considered as international flights whereas flights within a member State (from Spain to Spain) are classified as domestic flights. The assessment is based on scheduled passenger flights, including scheduled charter operations.”
B11: [2] Other producers along the air transport value chain are airports, ANSPs, manufacturers, lessors, GDS/CRSs, travel agents, ground services, catering, and maintenance.

Sheet noise cost airports (not used)
A2: Table 30: Average noise costs of major airports, € (2010) per LTO.
C3: Population outside agglomerations | D3: All population exposed to noise
A4: Country | B4: Airport
A5: Austria | B5: Vienna International Airport | C5: 10.8 | D5: 14.8
A6: Belgium | B6: Brussels National Airport | C6: 59.1 | D6: 76.9
A7: Czech Republic | B7: Prague Ruzyně International Airport | C7: 3.3 | D7: 4.2
A8: Denmark | B8: Billund Airport | C8: 0.7 | D8: 0.9
A9: Denmark | B9: Roskilde Airport | C9: 0.5 | D9: 0.7
A10: Denmark | B10: Copenhagen Airport | C10: 1.2 | D10: 5.8
A11: Finland | B11: Helsinki Vantaa Airport | C11: 0.1 | D11: 0.2
A12: France | B12: Lyon Saint Exupery Airport | C12: 7.3 | D12: 10.5
A13: France | B13: Paris Charles de Gaulle Airport | C13: 66.3 | D13: 110.6
A14: France | B14: Paris Orly Airport | C14: 2.8 | D14: 221.3
A15: France | B15: EuroAirport Basel-Mulhouse-Freiburg | C15: 2.4 | D15: 3.5
A16: Germany | B16: Hannover Langenhagen Airport | C16: 95.7 | D16: 115.8
... A21: Germany | B21: Frankfurt am Main Airport | C21: 136.3 | D21: 180.7
A22: Germany | B22: Berlin Tegel Airport | D22: 702.2
A23: Greece | B23: Athens International Airport | C23: 11.0 | D23: 0.0
A24: Hungary | B24: Budapest Ferihegy International Airport | C24: 12.0 | D24: 259.6
A25: Italy | B25: Bergamo Orio al Serio Airport | C25: 182.8 | D25: 234.3
A26: Italy | B26: Milan Linate Airport | C26: 187.7 | D26: 233.3
A27: Italy | B27: Milan Malpensa International Airport | C27: 36.2 | D27: 43.8
A28: Italy | B28: Naples International Airport | C28: 85.2 | D28: 385.5
A29: Italy | B29: Roma Fiumicino - Leonardo da Vinci Airport | C29: 26.9 | D29: 34.9
A30: Italy | B30: Turin International Airport | C30: 32.7 | D30: 50.7
A31: Luxembourg | B31: Luxembourg International Airport | C31: 249.3 | D31: 284.9
A32: Netherlands | B32: Amsterdam Schipol Airport | C32: 0.6 | D32: 38.8
A33: Poland | B33: Warszaw F.Chopin Airport | C33: 4.1 | D33: 27.1
A34: Portugal | B34: Lisbon Airport | C34: 5.9 | D34: 205.3
... A63: United Kingdom | B63: London Heathrow Airport | C63: 70.6 | D63: 652.1

Sheet cost of fuel (not used)
Q2: Fuel price
D3: value to be updated | Q3: IATA refinery price
B4: Fuel cost | D4: value updated (same as in "Conversions, Inflation, Cost of Fuel and Exchange Rate") | R4: Average for 2010 | S4: 91.4 | T4: $/bbl | U4: =S4/42 -> 2.1761905 | V4: $/gal | W4: Source:
R5: Average for 2011 | S5: 127.5 | T5: $/bbl | U5: =S5/42 -> 3.0357143 | V5: $/gal | W5: http://www.iata.org/whatwedo/Documents/economics/Industry-Outlook-Dec2012.pdf
C6: (US$/bbl) | F6: (US$/US gallon) | I6: (US$/kg) | L6: (€/Kg) | R6: Average for 2012 | S6: 129.6 | T6: $/bbl | U6: =S6/42 -> 3.0857143 | V6: $/gal
C7: Low (base-30%) | D7: Base | E7: High (base+30%) | F7: Low | G7: Base | H7: High | I7: Low | J7: Base | K7: High | L7: Low | M7: Base | N7: High | R7: Average for 2013 | S7: 124.6 | T7: $/bbl | U7: =S7/42 -> 2.9666667 | V7: $/gal
B8: 2017 | C8: =D8*(1-30%) -> 45.43 | D8: =S11 -> 64.9 | E8: =D8*(1+30%) -> 84.37 | F8: =G8*(1-30%) -> 1.0816667 | G8: =D8/$S$36 -> 1.5452381 | H8: =G8*(1+30%) -> 2.0088095 | I8: =F8/$S$40 -> 0.35279409 | J8: =G8/$S$40 -> 0.50399155 | K8: =H8/$S$40 -> 0.65518902 | L8: =I8*$S$18 -> 0.27459066 | M8: =J8*$S$18 -> 0.39227238 | N8: =K8*$S$18 -> 0.50995409 | R8: Average for 2014 | S8: 118.4 | T8: $/bbl | U8: =S8/42 -> 2.8190476 | V8: $/gal | W8: http://www.iata.org/whatwedo/Documents/economics/IATA-economic-briefing-financial-forecast-March-2014.pdf
B9: 2016 | C9: =D9*(1-30%) -> 36.47 | D9: =S10 -> 52.1 | E9: =D9*(1+30%) -> 67.73 | F9: =G9*(1-30%) -> 0.86833333 | G9: =D9/$S$36 -> 1.2404762 | H9: =G9*(1+30%) -> 1.612619 | I9: =F9/$S$40 -> 0.28321374 | J9: =G9/$S$40 -> 0.40459106 | K9: =H9/$S$40 -> 0.52596838 | L9: =I9*$S$18 -> 0.22043411 | M9: =J9*$S$18 -> 0.31490587 | N9: =K9*$S$18 -> 0.40937763 | R9: Average for 2015 | S9: 66.7 | T9: $/bbl | U9: =S9/42 -> 1.5880952 | V9: $/gal | W9: http://www.iata.org/whatwedo/Documents/economics/Central-forecast-Dec-2014-Figures.pdf
B10: 2015 | C10: =D10*(1-30%) -> 46.69 | D10: =S9 -> 66.7 | E10: =D10*(1+30%) -> 86.71 | F10: =G10*(1-30%) -> 1.1116667 | G10: =D10/$S$36 -> 1.5880952 | H10: =G10*(1+30%) -> 2.0645238 | I10: =F10/$S$40 -> 0.36257882 | J10: =G10/$S$40 -> 0.51796974 | K10: =H10/$S$40 -> 0.67336067 | L10: =I10*$S$18 -> 0.28220643 | M10: =J10*$S$18 -> 0.40315204 | N10: =K10*$S$18 -> 0.52409766 | R10: Average for 2016 | S10: 52.1 | T10: $/bbl | U10: =S10/42 -> 1.2404762 | V10: $/gal | W10: http://www.iata.org/whatwedo/Documents/economics/Central-forecast-end-year-2016-tables.pdf
B11: 2014 | C11: =D11*(1-30%) -> 82.88 | D11: =S8 -> 118.4 | E11: =D11*(1+30%) -> 153.92 | F11: =G11*(1-30%) -> 1.9733333 | G11: =D11/$S$36 -> 2.8190476 | H11: =G11*(1+30%) -> 3.6647619 | I11: =F11/$S$40 -> 0.64361818 | J11: =G11/$S$40 -> 0.91945454 | K11: =H11/$S$40 -> 1.1952909 | L11: =I11*$S$18 -> 0.50094815 | M11: =J11*$S$18 -> 0.71564021 | N11: =K11*$S$18 -> 0.93033227 | R11: Average for 2017 | S11: 64.9 | T11: $/bbl | U11: =S11/42 -> 1.5452381 | V11: $/gal
B12: 2013 | C12: =D12*(1-30%) -> 87.22 | D12: =S7 -> 124.6 | E12: =D12*(1+30%) -> 161.98 | F12: =G12*(1-30%) -> 2.0766667 | G12: =D12/$S$36 -> 2.9666667 | H12: =G12*(1+30%) -> 3.8566667 | I12: =F12/$S$40 -> 0.67732116 | J12: =G12/$S$40 -> 0.96760165 | K12: =H12/$S$40 -> 1.2578821 | L12: =I12*$S$18 -> 0.52718023 | M12: =J12*$S$18 -> 0.75311461 | N12: =K12*$S$18 -> 0.97904899 | R12: Average for 2018 | T12: $/bbl | U12: =S12/42 -> 0 | V12: $/gal
B13: 2012 | C13: =D13*(1-30%) -> 90.72 | D13: =S6 -> 129.6 | E13: =D13*(1+30%) -> 168.48 | F13: =G13*(1-30%) -> 2.16 | G13: =D13/$S$36 -> 3.0857143 | H13: =G13*(1+30%) -> 4.0114286 | I13: =F13/$S$40 -> 0.70450098 | J13: =G13/$S$40 -> 1.00643 | K13: =H13/$S$40 -> 1.308359 | L13: =I13*$S$18 -> 0.54833513 | M13: =J13*$S$18 -> 0.7833359 | N13: =K13*$S$18 -> 1.0183367
B14: 2011 | C14: =D14*(1-30%) -> 89.25 | D14: =S5 -> 127.5 | E14: =D14*(1+30%) -> 165.75 | F14: =G14*(1-30%) -> 2.125 | G14: =D14/$S$36 -> 3.0357143 | H14: =G14*(1+30%) -> 3.9464286 | I14: =F14/$S$40 -> 0.69308545 | J14: =G14/$S$40 -> 0.99012208 | K14: =H14/$S$40 -> 1.2871587 | L14: =I14*$S$18 -> 0.53945007 | M14: =J14*$S$18 -> 0.77064296 | N14: =K14*$S$18 -> 1.0018358
B15: 2010 | C15: =D15*(1-30%) -> 63.98 | D15: =S4 -> 91.4 | E15: =D15*(1+30%) -> 118.82 | F15: =G15*(1-30%) -> 1.5233333 | G15: =D15/$S$36 -> 2.1761905 | H15: =G15*(1+30%) -> 2.8290476 | I15: =F15/$S$40 -> 0.49684714 | J15: =G15/$S$40 -> 0.70978163 | K15: =H15/$S$40 -> 0.92271612 | L15: =I15*$S$18 -> 0.38671166 | M15: =J15*$S$18 -> 0.55244523 | N15: =K15*$S$18 -> 0.7181788 | Q15: Exchange rates 1 US$ to € | T15: 1 € to US$
R16: Average for 2010 | S16: 0.75431847 | T16: =1/S16 -> 1.3257 | W16: Source: | X16: http://sdw.ecb.europa.eu/
R17: Average for 2011 | S17: 0.7183908 | T17: =1/S17 -> 1.392 | X17: (go to Economic Concepts, Exchange rates, Bilateral)
C18: US$/bbl | D18: US$/US gallon | G18: €/Kg | R18: Average for 2012 | S18: 0.77833126 | T18: =1/S18 -> 1.2848
B19: Range | C19: Base | D19: Low | E19: Base | F19: High | G19: Low | H19: Base | I19: High | R19: Average for 2013 | S19: =1/T19 -> 0.76138267 | T19: 1.3134
B20: 2017 | C20: =D8 -> 64.9 | D20: =F8 -> 1.0816667 | E20: =G8 -> 1.5452381 | F20: =H8 -> 2.0088095 | G20: =L8 -> 0.27459066 | H20: =M8 -> 0.39227238 | I20: =N8 -> 0.50995409 | R20: Average for 2014 | S20: 0.75272 | T20: 1.3285
B21: 2016 | C21: =D9 -> 52.1 | D21: =F9 -> 0.86833333 | E21: =G9 -> 1.2404762 | F21: =H9 -> 1.612619 | G21: =L9 -> 0.22043411 | H21: =M9 -> 0.31490587 | I21: =N9 -> 0.40937763 | R21: Average for 2015 | S21: 0.90130689 | T21: 1.1095
B22: 2015 | C22: =D10 -> 66.7 | D22: =F10 -> 1.1116667 | E22: =G10 -> 1.5880952 | F22: =H10 -> 2.0645238 | G22: =L10 -> 0.28220643 | H22: =M10 -> 0.40315204 | I22: =N10 -> 0.52409766 | R22: Average for 2016 | S22: 0.90342398 | T22: 1.1069
B23: 2014 | C23: =D11 -> 118.4 | D23: =F11 -> 1.9733333 | E23: =G11 -> 2.8190476 | F23: =H11 -> 3.6647619 | G23: =L11 -> 0.50094815 | H23: =M11 -> 0.71564021 | I23: =N11 -> 0.93033227 | R23: Average for 2017
B24: 2013 | C24: =D12 -> 124.6 | D24: =F12 -> 2.0766667 | E24: =G12 -> 2.9666667 | F24: =H12 -> 3.8566667 | G24: =L12 -> 0.52718023 | H24: =M12 -> 0.75311461 | I24: =N12 -> 0.97904899 | R24: Average for 2018
B25: 2012 | C25: =D13 -> 129.6 | D25: =F13 -> 2.16 | E25: =G13 -> 3.0857143 | F25: =H13 -> 4.0114286 | G25: =L13 -> 0.54833513 | H25: =M13 -> 0.7833359 | I25: =N13 -> 1.0183367
B26: 2011 | C26: =D14 -> 127.5 | D26: =F14 -> 2.125 | E26: =G14 -> 3.0357143 | F26: =H14 -> 3.9464286 | G26: =L14 -> 0.53945007 | H26: =M14 -> 0.77064296 | I26: =N14 -> 1.0018358
B27: 2010 | C27: =D15 -> 91.4 | D27: =F15 -> 1.5233333 | E27: =G15 -> 2.1761905 | F27: =H15 -> 2.8290476 | G27: =L15 -> 0.38671166 | H27: =M15 -> 0.55244523 | I27: =N15 -> 0.7181788
Q29: Conversion factors
R30: 1 barrel = | S30: 158.984 litres
S31: 42 US gallons
S32: 0.136 tonne (approx)
R33: 1 tonne (metrics - 1000 kg) | S33: 326 US gal of jet fuel
S34: 1,235 l of jet fuel
S35: 7.8 | T35: barrels
R36: 1 barrel (bbl) | S36: 42 | T36: US gallons
S37: 159 | T37: litres of jet fuel
S38: 0.128 | T38: ton = 128 kg
R39: 1 US gallon of jet fuel (gal) | S39: 3.7854 | T39: liter
S40: 3.066 | T40: kg
R41: 6.746 | S41: lb
R43: Density of kerosene | S43: 0.81 | T43: kg/litre
R44: 1 litre of fuel (l) | S44: 0.265 | T44: gal
R45: 1 kilogramme of fuel (kg) | S45: 2.2 | T45: lb
R46: 1 pound of fuel (lb) | S46: 0.454 | T46: kg

Sheet Injury (not used)
A1: Value of avoided fatality
A2: Value [1]: | B2: 2.5 | C2: million | E2: =E29*dollar -> #REF!
A4: Value [2]: | B4: 2.3 | C4: million | E4: =B4*index/index2006 -> #REF!
A6: Value [3]:
A7: Country | B7: Official values in use | C7: UNITE VOSL | J7: Country | K7: Official values in use | L7: UNITE VSL
B8: (€m) | C8: (€m) | K8: (€m) | L8: (€m)
A9: Austria | B9: 1.8 | C9: 1.99 | E9: =B9*factor98 -> 2.6180464 | F9: =C9*factor98 -> 2.8943957 | J9: Austria | K9: 2.09 | L9: 2.31
A10: Belgium | B10: 0.48 | C10: 1.98 | E10: =B10*factor98 -> 0.6981457 | F10: =C10*factor98 -> 2.879851 | J10: Belgium | K10: 0.55 | L10: 2.30
A11: Denmark | B11: 0.61 | C11: 2.12 | E11: =B11*factor98 -> 0.88722682 | F11: =C11*factor98 -> 3.0834768 | J11: Denmark | K11: 0.71 | L11: 2.46
A12: Estonia | B12: n.a. | C12: 0.76 | E12: n.a. | F12: =C12*factor98 -> 1.1053974 | J12: Estonia | K12: n/a | L12: 0.87
A13: Finland | B13: 1.06 | C13: 1.82 | E13: =B13*factor98 -> 1.5417384 | F13: =C13*factor98 -> 2.6471358 | J13: Finland | K13: 1.23 | L13: 2.11
A14: France | B14: 0.73 | C14: 1.76 | E14: =B14*factor98 -> 1.0617632 | F14: =C14*factor98 -> 2.5598675 | J14: France | K14: 0.84 | L14: 2.04
A15: Germany | B15: 1.04 | C15: 1.92 | E15: =B15*factor98 -> 1.512649 | F15: =C15*factor98 -> 2.7925828 | J15: Germany | K15: 1.20 | L15: 2.23
A16: Greece | B16: 0.17 | C16: 1.18 | E16: =B16*factor98 -> 0.24725993 | F16: =C16*factor98 -> 1.7162748 | J16: Greece | K16: 0.20 | L16: 1.36
A17: Hungary | B17: n.a. | C17: 0.88 | E17: n.a. | F17: =C17*factor98 -> 1.2799338 | J17: Hungary | K17: n/a | L17: 1.02
A18: Ireland | B18: 1.23 | C18: 1.93 | E18: =B18*factor98 -> 1.7889983 | F18: =C18*factor98 -> 2.8071275 | J18: Ireland | K18: 1.43 | L18: 2.24
A19: Italy | B19: n.a. | C19: 1.79 | E19: n.a. | F19: =C19*factor98 -> 2.6035017 | J19: Italy | K19: n/a | L19: 2.08
A20: Luxembourg | B20: n.a. | C20: 3.13 | E20: n.a. | F20: =C20*factor98 -> 4.5524917 | J20: Luxembourg | K20: n/a | L20: 3.634
A21: Netherlands | B21: 0.15 | C21: 2.01 | E21: =B21*factor98 -> 0.21817053 | F21: =C21*factor98 -> 2.9234851 | J21: Netherlands | K21: 0.18 | L21: 2.33
A22: Norway | B22: 1.77 | C22: 2.28 | E22: =B22*factor98 -> 2.5744123 | F22: =C22*factor98 -> 3.3161921 | J22: Norway | K22: 2.06 | L22: 2.65
A23: Portugal | B23: 0.04 | C23: 1.33 | E23: =B23*factor98 -> 0.058178808 | F23: =C23*factor98 -> 1.9344454 | J23: Portugal | K23: 0.04 | L23: 1.54
A24: Spain | B24: 0.07 | C24: 1.43 | E24: =B24*factor98 -> 0.10181291 | F24: =C24*factor98 -> 2.0798924 | J24: Spain | K24: 0.07 | L24: 1.65
A25: Sweden | B25: 1.76 | C25: 1.81 | E25: =B25*factor98 -> 2.5598675 | F25: =C25*factor98 -> 2.6325911 | J25: Sweden | K25: 2.04 | L25: 2.10
A26: Switzerland | B26: n.a. | C26: 2.16 | E26: n.a. | F26: =C26*factor98 -> 3.1416556 | J26: Switzerland | K26: n/a | L26: 2.50
A27: United Kingdom | B27: 1.81 | C27: 1.8 | E27: =B27*factor98 -> 2.6325911 | F27: =C27*factor98 -> 2.6180464 | J27: United Kingdom | K27: 2.10 | L27: 2.09
A29: Source [1]: | B29: 5.8 | E29: =B29*index/#REF! -> #REF!
A31: Value of avoided injuries
A32: Value:
A33: Minor injury | B33: 35401 | E33: =E38*index/#REF!*dollar -> #REF!
A34: Major injury | B34: 479801 | E34: =E39*index/#REF!*dollar -> #REF!
A36: Source:
A37: Injury | B37: WTP Value | C37: Emergency/Medical | D37: Legal/Court | E37: Total Value
A38: Minor | B38: 34000 | C38: 2000 | D38: 2500 | E38: =SUM(B38:D38) -> 38500
A39: Major | B39: 482000 | C39: 27600 | D39: 12200 | E39: =SUM(B39:D39) -> 521800

Sheet Flight OPS costs (not used)
A1: Not used for Ed. 9 | R1: US inflation since 2012 -> 2016 | T1: 0.045 | U1: http://www.usinflationcalculator.com/ | AA1: US inflation since 2012 -> 2016 | AC1: 0.045 | AD1: http://www.usinflationcalculator.com/
I2: US$: | J2: 0.7793 | R2: US$: | S2: 0.75362 | T2: Xchange rate = 2014 unchanged | AA2: US$: | AB2: 0.75362 | AC2: Xchange rate = 2014 unchanged
R3: not updated as 2014 index not available - Sept 2014 | AA3: not updated as 2014 index not available - Sept 2014
A4: Table value US$ 2012 | I4: Table value € 2013 | R4: Table value € 2016 | AA4: Table value € 2016
A5: in US$ | I5: in € | R5: in € | AA5: in US $
A6: Flight Operations | B6: Flight Ops. $/AC[1] | C6: Flight Ops. $/FH | D6: Flight Ops. $/FC | E6: Flight Ops. $/ASK | F6: Flight Ops. $/ATK | I6: Flight Operations | J6: Flight Ops./ Aircraft | K6: Flight Ops. /Flight Hour | L6: Flight Ops. Flight Cycle | M6: Flight Ops. /ASK | N6: Flight Ops. $/ATK | R6: Flight Operations | S6: Flight Ops./ Aircraft | T6: Flight Ops. /Flight Hour | U6: Flight Ops. Flight Cycle | V6: Flight Ops. /ASK | W6: Flight Ops. $/ATK | AA6: Flight Operations | AB6: Flight Ops./ Aircraft | AC6: Flight Ops. /Flight Hour | AD6: Flight Ops. Flight Cycle | AE6: Flight Ops. /ASK | AF6: Flight Ops. $/ATK
E7: (US Cents) | F7: (US Cents) | M7: (€ Cents) | N7: (e Cents) | V7: (€ Cents) | W7: (e Cents) | AE7: (US$ Cents) | AF7: (US$ Cents)
A8: B737 NG | B8: 13.3 | C8: 4152 | D8: 7428 | E8: 4.18 | F8: 34.16 | I8: B737 NG | J8: 10.4 mil | K8: =C8*$J$2 -> 3235.6536 | L8: =D8*$J$2 -> 5788.6404 | M8: =E8*$J$2 -> 3.257474 | N8: =F8*$J$2 -> 26.620888 | R8: B737 NG | S8: =B8*$S$2*(1+$T$1) -> 10.474188 | T8: =C8*$S$2*(1+$T$1) -> 3269.8366 | U8: =D8*$S$2*(1+$T$1) -> 5849.7944 | V8: =E8*$S$2*(1+$T$1) -> 3.2918875 | W8: =F8*$S$2*(1+$T$1) -> 26.902124 | AA8: B737 NG | AB8: =B8*(1+$AC$1/100) -> 13.305985 | AC8: =C8*(1+$AC$1/100) -> 4153.8684 | AD8: =D8*(1+$AC$1/100) -> 7431.3426 | AE8: =E8*(1+$AC$1/100) -> 4.181881 | AF8: =F8*(1+$AC$1/100) -> 34.175372
A9: A320 Family | B9: 14.5 | C9: 4633 | D9: 9722 | E9: 4.56 | F9: 36.8 | I9: A320 Family | J9: 11.3 mil | K9: =C9*$J$2 -> 3610.4969 | L9: =D9*$J$2 -> 7576.3546 | M9: =E9*$J$2 -> 3.553608 | N9: =F9*$J$2 -> 28.67824 | R9: A320 Family | S9: =B9*$S$2*(1+$T$1) -> 11.419227 | T9: =C9*$S$2*(1+$T$1) -> 3648.6399 | U9: =D9*$S$2*(1+$T$1) -> 7656.3949 | V9: =E9*$S$2*(1+$T$1) -> 3.59115 | W9: =F9*$S$2*(1+$T$1) -> 28.981211 | AA9: A320 Family | AB9: =B9*(1+$AC$1/100) -> 14.506525 | AC9: =C9*(1+$AC$1/100) -> 4635.0849 | AD9: =D9*(1+$AC$1/100) -> 9726.3749 | AE9: =E9*(1+$AC$1/100) -> 4.562052 | AF9: =F9*(1+$AC$1/100) -> 36.81656
A10: B737 Classic | B10: 13.3 | C10: 4624 | D10: 6315 | E10: 5.36 | F10: 46.21 | I10: B737 Classic | J10: 10.4 mil | K10: =C10*$J$2 -> 3603.4832 | L10: =D10*$J$2 -> 4921.2795 | M10: =E10*$J$2 -> 4.177048 | N10: =F10*$J$2 -> 36.011453 | R10: B737 Classic | S10: =B10*$S$2*(1+$T$1) -> 10.474188 | T10: =C10*$S$2*(1+$T$1) -> 3641.5521 | U10: =D10*$S$2*(1+$T$1) -> 4973.2703 | V10: =E10*$S$2*(1+$T$1) -> 4.2211763 | W10: =F10*$S$2*(1+$T$1) -> 36.391895 | AA10: B737 Classic | AB10: =B10*(1+$AC$1/100) -> 13.305985 | AC10: =C10*(1+$AC$1/100) -> 4626.0808 | AD10: =D10*(1+$AC$1/100) -> 6317.8418 | AE10: =E10*(1+$AC$1/100) -> 5.362412 | AF10: =F10*(1+$AC$1/100) -> 46.230795
A11: B777 | B11: 48.6 | C11: 11220 | D11: 64616 | E11: 4.59 | F11: 27.33 | I11: B777 | J11: 37.9 mil | K11: =C11*$J$2 -> 8743.746 | L11: =D11*$J$2 -> 50355.249 | M11: =E11*$J$2 -> 3.576987 | N11: =F11*$J$2 -> 21.298269 | R11: B777 | S11: =B11*$S$2*(1+$T$1) -> 38.274099 | T11: =C11*$S$2*(1+$T$1) -> 8836.1191 | U11: =D11*$S$2*(1+$T$1) -> 50887.226 | V11: =E11*$S$2*(1+$T$1) -> 3.614776 | W11: =F11*$S$2*(1+$T$1) -> 21.523274 | AA11: B777 | AB11: =B11*(1+$AC$1/100) -> 48.62187 | AC11: =C11*(1+$AC$1/100) -> 11225.049 | AD11: =D11*(1+$AC$1/100) -> 64645.077 | AE11: =E11*(1+$AC$1/100) -> 4.5920655 | AF11: =F11*(1+$AC$1/100) -> 27.342298
A12: A330 | B12: 33.8 | C12: 8800 | D12: 38455 | E12: 4.24 | F12: 26.93 | I12: A330 | J12: 26.3 mil | K12: =C12*$J$2 -> 6857.84 | L12: =D12*$J$2 -> 29967.981 | M12: =E12*$J$2 -> 3.304232 | N12: =F12*$J$2 -> 20.986549 | R12: A330 | S12: =B12*$S$2*(1+$T$1) -> 26.618612 | T12: =C12*$S$2*(1+$T$1) -> 6930.2895 | U12: =D12*$S$2*(1+$T$1) -> 30284.578 | V12: =E12*$S$2*(1+$T$1) -> 3.3391395 | W12: =F12*$S$2*(1+$T$1) -> 21.208261 | AA12: A330 | AB12: =B12*(1+$AC$1/100) -> 33.81521 | AC12: =C12*(1+$AC$1/100) -> 8803.96 | AD12: =D12*(1+$AC$1/100) -> 38472.305 | AE12: =E12*(1+$AC$1/100) -> 4.241908 | AF12: =F12*(1+$AC$1/100) -> 26.942119
A13: B747 | B13: 43.1 | C13: 13975 | D13: 86616 | E13: 4.33 | F13: 30.93 | I13: B747 | J13: 33.6 mil | K13: =C13*$J$2 -> 10890.718 | L13: =D13*$J$2 -> 67499.849 | M13: =E13*$J$2 -> 3.374369 | N13: =F13*$J$2 -> 24.103749 | R13: B747 | S13: =B13*$S$2*(1+$T$1) -> 33.942668 | T13: =C13*$S$2*(1+$T$1) -> 11005.772 | U13: =D13*$S$2*(1+$T$1) -> 68212.95 | V13: =E13*$S$2*(1+$T$1) -> 3.4100175 | W13: =F13*$S$2*(1+$T$1) -> 24.358393 | AA13: B747 | AB13: =B13*(1+$AC$1/100) -> 43.119395 | AC13: =C13*(1+$AC$1/100) -> 13981.289 | AD13: =D13*(1+$AC$1/100) -> 86654.977 | AE13: =E13*(1+$AC$1/100) -> 4.3319485 | AF13: =F13*(1+$AC$1/100) -> 30.943919
A14: A340 | B14: 48.5 | C14: 11824 | D14: 88705 | E14: 5.73 | F14: 32.46 | I14: A340 | J14: 37.8 mil | K14: =C14*$J$2 -> 9214.4432 | L14: =D14*$J$2 -> 69127.807 | M14: =E14*$J$2 -> 4.465389 | N14: =F14*$J$2 -> 25.296078 | R14: A340 | S14: =B14*$S$2*(1+$T$1) -> 38.195346 | T14: =C14*$S$2*(1+$T$1) -> 9311.789 | U14: =D14*$S$2*(1+$T$1) -> 69858.106 | V14: =E14*$S$2*(1+$T$1) -> 4.5125635 | W14: =F14*$S$2*(1+$T$1) -> 25.563318 | AA14: A340 | AB14: =B14*(1+$AC$1/100) -> 48.521825 | AC14: =C14*(1+$AC$1/100) -> 11829.321 | AD14: =D14*(1+$AC$1/100) -> 88744.917 | AE14: =E14*(1+$AC$1/100) -> 5.7325785 | AF14: =F14*(1+$AC$1/100) -> 32.474607
A15: B767 | B15: 33.8 | C15: 8002 | D15: 51887 | E15: 4.78 | F15: 25.68 | I15: B767 | J15: 26.3 mil | K15: =C15*$J$2 -> 6235.9586 | L15: =D15*$J$2 -> 40435.539 | M15: =E15*$J$2 -> 3.725054 | N15: =F15*$J$2 -> 20.012424 | R15: B767 | S15: =B15*$S$2*(1+$T$1) -> 26.618612 | T15: =C15*$S$2*(1+$T$1) -> 6301.8383 | U15: =D15*$S$2*(1+$T$1) -> 40862.72 | V15: =E15*$S$2*(1+$T$1) -> 3.7644073 | W15: =F15*$S$2*(1+$T$1) -> 20.223845 | AA15: B767 | AB15: =B15*(1+$AC$1/100) -> 33.81521 | AC15: =C15*(1+$AC$1/100) -> 8005.6009 | AD15: =D15*(1+$AC$1/100) -> 51910.349 | AE15: =E15*(1+$AC$1/100) -> 4.782151 | AF15: =F15*(1+$AC$1/100) -> 25.691556
A16: A380 | B16: 61.7 | C16: 18837 | D16: 181920 | E16: 5.02 | F16: 40.03 | I16: A380 | J16: 48.1 mil | K16: =C16*$J$2 -> 14679.674 | L16: =D16*$J$2 -> 141770.26 | M16: =E16*$J$2 -> 3.912086 | N16: =F16*$J$2 -> 31.195379 | R16: A380 | S16: =B16*$S$2*(1+$T$1) -> 48.59078 | T16: =C16*$S$2*(1+$T$1) -> 14834.757 | U16: =D16*$S$2*(1+$T$1) -> 143267.99 | V16: =E16*$S$2*(1+$T$1) -> 3.9534152 | W16: =F16*$S$2*(1+$T$1) -> 31.524942 | AA16: A380 | AB16: =B16*(1+$AC$1/100) -> 61.727765 | AC16: =C16*(1+$AC$1/100) -> 18845.477 | AD16: =D16*(1+$AC$1/100) -> 182001.86 | AE16: =E16*(1+$AC$1/100) -> 5.022259 | AF16: =F16*(1+$AC$1/100) -> 40.048014
A17: Regional Jet* | B17: 8.8 | C17: 3437 | D17: 5462 | E17: 6.05 | F17: 46.9 | I17: Regional Jet* | J17: 6.9 mil | K17: =C17*$J$2 -> 2678.4541 | L17: =D17*$J$2 -> 4256.5366 | M17: =E17*$J$2 -> 4.714765 | N17: =F17*$J$2 -> 36.54917 | R17: Regional Jet* | S17: =B17*$S$2*(1+$T$1) -> 6.9302895 | T17: =C17*$S$2*(1+$T$1) -> 2706.7506 | U17: =D17*$S$2*(1+$T$1) -> 4301.5047 | V17: =E17*$S$2*(1+$T$1) -> 4.764574 | W17: =F17*$S$2*(1+$T$1) -> 36.935293 | AA17: Regional Jet* | AB17: =B17*(1+$AC$1/100) -> 8.80396 | AC17: =C17*(1+$AC$1/100) -> 3438.5467 | AD17: =D17*(1+$AC$1/100) -> 5464.4579 | AE17: =E17*(1+$AC$1/100) -> 6.0527225 | AF17: =F17*(1+$AC$1/100) -> 46.921105
I18: ASK: Available Seat Kilometre | R18: ASK: Available Seat Kilometre | AA18: ASK: Available Seat Kilometre
I19: ATK: Available Ton Kilometre | R19: ATK: Available Ton Kilometre | AA19: ATK: Available Ton Kilometre
T23: =S8*(1+0.045) -> 10.945526
A26: source | AA26: =275.5/657.8 -> 0.41882031
A27: http://www.iata.org/whatwedo/workgroups/Documents/acc-2013-gva/0930-1015_AOCTF_FY2012_Report_FERJAN.pdf
